Workbook

Sheet Leia primeiro
A2: FROID NR-1 — simulador comercial
A4: Células de fundo escuro são ENTRADAS. Todo o resto é fórmula e recalcula sozinho.
A6: Receita
A7: A conta de uma proposta. Efetivo, unidades, desconto e a tabela de preços de um lado; fatura decomposta faixa a faixa do outro.
A8: Unidade é ESTABELECIMENTO, não departamento. Cinco setores no mesmo endereço são uma base, não cinco. Errar isso multiplica a fatura.
A10: Cenários
A11: A mesma tabela aplicada a doze efetivos. Serve para ver onde o preço por trabalhador cai e onde o contrato fica pequeno demais para o trabalho que dá.
A13: Anonimato
A14: A parte que preço nenhum resolve. Diz quantas respostas cada setor precisa para aparecer no relatório.
A15: Os pisos vêm do banco e não são negociáveis comercialmente. Um recorte suprimido é o piso funcionando, não defeito — mas isso precisa estar combinado ANTES do contrato.
A17: Alavancas
A18: Compara a tabela vigente com cenários de reajuste. Não altera nada: é só para decidir.
... A25: O que esta planilha NÃO faz: não estima custo, não tem margem e não conhece preço de concorrente. É receita bruta. Enquanto o custo de operar uma campanha não estiver medido, ela mostra quanto entra — não quanto sobra.

Sheet Receita
A1: FROID NR-1 — simulador de receita
A2: Células escuras são entradas: mude e o resto recalcula. As faixas são cumulativas e incidem sobre o efetivo total.
A4: Cliente
A5: Trabalhadores (efetivo total) | B5: 300
A6: Unidades (estabelecimentos) | B6: 1 | C6: departamento no mesmo endereço NÃO é unidade
A7: Desconto aplicado | B7: 0
A9: Tabela de preços
A10: Componente | B10: Valor | C10: Até
A11: Base da plataforma, por estabelecimento / mês | B11: 500
A12: Faixa 1 — por trabalhador / mês | B12: 15 | C12: 100
A13: Faixa 2 — por trabalhador / mês | B13: 12.5 | C13: 300
A14: Faixa 3 — por trabalhador / mês | B14: 9.3 | C14: 1000
A15: Faixa 4 — por trabalhador / mês | B15: 6.55 | C15: acima
A17: Implantação (cobrança única) | B17: 0 | C17: hoje em branco na proposta
A19: Decomposição da fatura mensal
A20: Componente | B20: Trabalhadores na faixa | C20: Subtotal / mês
A21: Base da plataforma | B21: =B6 | C21: =B6*B11
A22: Faixa 1 (1 a 100) | B22: =MEDIAN(0,$B$5,$C$12) | C22: =B22*B12
A23: Faixa 2 (101 a 300) | B23: =MEDIAN(0,$B$5-$C$12,$C$13-$C$12) | C23: =B23*B13
A24: Faixa 3 (301 a 1.000) | B24: =MEDIAN(0,$B$5-$C$13,$C$14-$C$13) | C24: =B24*B14
A25: Faixa 4 (acima de 1.000) | B25: =MAX(0,$B$5-$C$14) | C25: =B25*B15
A26: Confere: soma das faixas | B26: =SUM(B22:B25) | C26: deve igualar o efetivo
A28: Resultado
A29: Mensal — tabela cheia | B29: =SUM(C21:C25)
A30: Mensal — com desconto | B30: =B29*(1-B7)
A31: Anual — com desconto | B31: =B30*12
A32: Ano 1 — anual + implantação | B32: =B31+B17
A33: Por trabalhador / ano | B33: =IF(B5=0,"",B31/B5)
A34: Por trabalhador / mês | B34: =IF(B5=0,"",B30/B5)
A35: Campanhas por ano | B35: 2 | D35: linha de base + verificação de eficácia
A36: Receita por campanha | B36: =IF(B35=0,"",B31/B35)
A37: É esse número que o cliente compara com um orçamento de consultoria. Vale saber qual é antes da reunião.

Sheet Cenários
A1: Mesma tabela, efetivos diferentes
A2: Usa a tabela de preços da aba Receita. Mude lá e esta recalcula. Unidades fixadas em 1.
A4: Trabalhadores | B4: Mensal | C4: Anual | D4: Por trab./ano | E4: Por trab./mês | F4: Receita/campanha
A5: 15 | B5: =Receita!$B$11+MEDIAN(0,A5,Receita!$C$12)*Receita!$B$12+MEDIAN(0,A5-Receita!$C$12,Receita!$C$13-Receita!$C$12)*Receita!$B$13+MEDIAN(0,A5-Receita!$C$13,Receita!$C$14-Receita!$C$13)*Receita!$B$14+MAX(0,A5-Receita!$C$14)*Receita!$B$15 | C5: =B5*12 | D5: =C5/A5 | E5: =B5/A5 | F5: =IF(Receita!$B$35=0,"",C5/Receita!$B$35)
A6: 25 | B6: =Receita!$B$11+MEDIAN(0,A6,Receita!$C$12)*Receita!$B$12+MEDIAN(0,A6-Receita!$C$12,Receita!$C$13-Receita!$C$12)*Receita!$B$13+MEDIAN(0,A6-Receita!$C$13,Receita!$C$14-Receita!$C$13)*Receita!$B$14+MAX(0,A6-Receita!$C$14)*Receita!$B$15 | C6: =B6*12 | D6: =C6/A6 | E6: =B6/A6 | F6: =IF(Receita!$B$35=0,"",C6/Receita!$B$35)
A7: 40 | B7: =Receita!$B$11+MEDIAN(0,A7,Receita!$C$12)*Receita!$B$12+MEDIAN(0,A7-Receita!$C$12,Receita!$C$13-Receita!$C$12)*Receita!$B$13+MEDIAN(0,A7-Receita!$C$13,Receita!$C$14-Receita!$C$13)*Receita!$B$14+MAX(0,A7-Receita!$C$14)*Receita!$B$15 | C7: =B7*12 | D7: =C7/A7 | E7: =B7/A7 | F7: =IF(Receita!$B$35=0,"",C7/Receita!$B$35)
A8: 50 | B8: =Receita!$B$11+MEDIAN(0,A8,Receita!$C$12)*Receita!$B$12+MEDIAN(0,A8-Receita!$C$12,Receita!$C$13-Receita!$C$12)*Receita!$B$13+MEDIAN(0,A8-Receita!$C$13,Receita!$C$14-Receita!$C$13)*Receita!$B$14+MAX(0,A8-Receita!$C$14)*Receita!$B$15 | C8: =B8*12 | D8: =C8/A8 | E8: =B8/A8 | F8: =IF(Receita!$B$35=0,"",C8/Receita!$B$35)
A9: 75 | B9: =Receita!$B$11+MEDIAN(0,A9,Receita!$C$12)*Receita!$B$12+MEDIAN(0,A9-Receita!$C$12,Receita!$C$13-Receita!$C$12)*Receita!$B$13+MEDIAN(0,A9-Receita!$C$13,Receita!$C$14-Receita!$C$13)*Receita!$B$14+MAX(0,A9-Receita!$C$14)*Receita!$B$15 | C9: =B9*12 | D9: =C9/A9 | E9: =B9/A9 | F9: =IF(Receita!$B$35=0,"",C9/Receita!$B$35)
A10: 100 | B10: =Receita!$B$11+MEDIAN(0,A10,Receita!$C$12)*Receita!$B$12+MEDIAN(0,A10-Receita!$C$12,Receita!$C$13-Receita!$C$12)*Receita!$B$13+MEDIAN(0,A10-Receita!$C$13,Receita!$C$14-Receita!$C$13)*Receita!$B$14+MAX(0,A10-Receita!$C$14)*Receita!$B$15 | C10: =B10*12 | D10: =C10/A10 | E10: =B10/A10 | F10: =IF(Receita!$B$35=0,"",C10/Receita!$B$35)
A11: 150 | B11: =Receita!$B$11+MEDIAN(0,A11,Receita!$C$12)*Receita!$B$12+MEDIAN(0,A11-Receita!$C$12,Receita!$C$13-Receita!$C$12)*Receita!$B$13+MEDIAN(0,A11-Receita!$C$13,Receita!$C$14-Receita!$C$13)*Receita!$B$14+MAX(0,A11-Receita!$C$14)*Receita!$B$15 | C11: =B11*12 | D11: =C11/A11 | E11: =B11/A11 | F11: =IF(Receita!$B$35=0,"",C11/Receita!$B$35)
A12: 200 | B12: =Receita!$B$11+MEDIAN(0,A12,Receita!$C$12)*Receita!$B$12+MEDIAN(0,A12-Receita!$C$12,Receita!$C$13-Receita!$C$12)*Receita!$B$13+MEDIAN(0,A12-Receita!$C$13,Receita!$C$14-Receita!$C$13)*Receita!$B$14+MAX(0,A12-Receita!$C$14)*Receita!$B$15 | C12: =B12*12 | D12: =C12/A12 | E12: =B12/A12 | F12: =IF(Receita!$B$35=0,"",C12/Receita!$B$35)
A13: 300 | B13: =Receita!$B$11+MEDIAN(0,A13,Receita!$C$12)*Receita!$B$12+MEDIAN(0,A13-Receita!$C$12,Receita!$C$13-Receita!$C$12)*Receita!$B$13+MEDIAN(0,A13-Receita!$C$13,Receita!$C$14-Receita!$C$13)*Receita!$B$14+MAX(0,A13-Receita!$C$14)*Receita!$B$15 | C13: =B13*12 | D13: =C13/A13 | E13: =B13/A13 | F13: =IF(Receita!$B$35=0,"",C13/Receita!$B$35)
A14: 500 | B14: =Receita!$B$11+MEDIAN(0,A14,Receita!$C$12)*Receita!$B$12+MEDIAN(0,A14-Receita!$C$12,Receita!$C$13-Receita!$C$12)*Receita!$B$13+MEDIAN(0,A14-Receita!$C$13,Receita!$C$14-Receita!$C$13)*Receita!$B$14+MAX(0,A14-Receita!$C$14)*Receita!$B$15 | C14: =B14*12 | D14: =C14/A14 | E14: =B14/A14 | F14: =IF(Receita!$B$35=0,"",C14/Receita!$B$35)
A15: 750 | B15: =Receita!$B$11+MEDIAN(0,A15,Receita!$C$12)*Receita!$B$12+MEDIAN(0,A15-Receita!$C$12,Receita!$C$13-Receita!$C$12)*Receita!$B$13+MEDIAN(0,A15-Receita!$C$13,Receita!$C$14-Receita!$C$13)*Receita!$B$14+MAX(0,A15-Receita!$C$14)*Receita!$B$15 | C15: =B15*12 | D15: =C15/A15 | E15: =B15/A15 | F15: =IF(Receita!$B$35=0,"",C15/Receita!$B$35)
A16: 1000 | B16: =Receita!$B$11+MEDIAN(0,A16,Receita!$C$12)*Receita!$B$12+MEDIAN(0,A16-Receita!$C$12,Receita!$C$13-Receita!$C$12)*Receita!$B$13+MEDIAN(0,A16-Receita!$C$13,Receita!$C$14-Receita!$C$13)*Receita!$B$14+MAX(0,A16-Receita!$C$14)*Receita!$B$15 | C16: =B16*12 | D16: =C16/A16 | E16: =B16/A16 | F16: =IF(Receita!$B$35=0,"",C16/Receita!$B$35)
... A19: 5000 | B19: =Receita!$B$11+MEDIAN(0,A19,Receita!$C$12)*Receita!$B$12+MEDIAN(0,A19-Receita!$C$12,Receita!$C$13-Receita!$C$12)*Receita!$B$13+MEDIAN(0,A19-Receita!$C$13,Receita!$C$14-Receita!$C$13)*Receita!$B$14+MAX(0,A19-Receita!$C$14)*Receita!$B$15 | C19: =B19*12 | D19: =C19/A19 | E19: =B19/A19 | F19: =IF(Receita!$B$35=0,"",C19/Receita!$B$35)
A21: Os efetivos de 50 e 75 estão aqui de propósito: abaixo de cerca de 75 a campanha não atinge o piso de anonimato e não produz resultado liberável. Ver a aba Anonimato antes de propor.

Sheet Anonimato
A1: Quantas respostas para o resultado sair
A2: Os pisos NÃO são configuráveis comercialmente: estão no banco e existem para proteger o trabalhador. Esta aba diz o que a adesão precisa ser, não o contrário.
A4: Pisos do sistema
A5: Piso da campanha (respostas substantivas) | B5: 15 | D5: froid_nr1_min_cohort_total()
A6: Piso por recorte (setor / unidade) | B6: 10 | D6: froid_nr1_min_cohort_cut()
A7: Cobertura mínima para a resposta contar | B7: 0.5 | D7: das dimensões do instrumento
A9: Adesão esperada
A10: Adesão (respondem) | B10: 0.7
A11: Dos que respondem, quantos completam o suficiente | B11: 0.85
A12: Taxa efetiva (substantivas / convidados) | B12: =B10*B11
A14: Departamentos
A15: Departamento | B15: Efetivo | C15: Respostas substantivas previstas | D15: Publica? | E15: Adesão mínima para publicar | F15: Folga
A16: Operações | B16: 120 | C16: =ROUND(B16*$B$12,0) | D16: =IF(C16>=$B$6,"sim","SUPRIMIDO") | E16: =IF(B16=0,"",$B$6/B16/$B$11) | F16: =C16-$B$6
A17: Comercial | B17: 80 | C17: =ROUND(B17*$B$12,0) | D17: =IF(C17>=$B$6,"sim","SUPRIMIDO") | E17: =IF(B17=0,"",$B$6/B17/$B$11) | F17: =C17-$B$6
A18: Administrativo | B18: 50 | C18: =ROUND(B18*$B$12,0) | D18: =IF(C18>=$B$6,"sim","SUPRIMIDO") | E18: =IF(B18=0,"",$B$6/B18/$B$11) | F18: =C18-$B$6
A19: Logística | B19: 30 | C19: =ROUND(B19*$B$12,0) | D19: =IF(C19>=$B$6,"sim","SUPRIMIDO") | E19: =IF(B19=0,"",$B$6/B19/$B$11) | F19: =C19-$B$6
A20: Diretoria | B20: 20 | C20: =ROUND(B20*$B$12,0) | D20: =IF(C20>=$B$6,"sim","SUPRIMIDO") | E20: =IF(B20=0,"",$B$6/B20/$B$11) | F20: =C20-$B$6
A21: Total da campanha | B21: =SUM(B16:B20) | C21: =SUM(C16:C20) | D21: =IF(C21>=$B$5,"campanha liberada","ABAIXO DO PISO")
A23: O menor departamento é quem manda: leia a coluna “Adesão mínima para publicar” de baixo para cima. Ela não é o piso dividido pelo efetivo — embute também a completude, porque resposta que não cobre metade das dimensões não conta. É por isso que a exigência do setor pequeno é maior do que a conta de cabeça sugere, e é sobre esse setor que o cliente vai perguntar na reunião.
A25: Recorte suprimido não é falha do FROID: é o piso de anonimato funcionando. Combinar isso ANTES do contrato evita a conversa ruim depois da campanha encerrada.

Sheet Alavancas
A1: E se a tabela mudasse?
A2: Compara a tabela vigente com cenários de reajuste, no efetivo informado na aba Receita. Nada aqui altera a tabela real.
A4: Efetivo simulado | B4: =Receita!B5
A6: Cenário | B6: Base/mês | C6: Faixa 1 | D6: Faixa 2 | E6: Faixa 3 | F6: Faixa 4 | G6: Mensal | H6: Anual | I6: Variação
A7: Vigente | B7: 500 | C7: 15 | D7: 12.5 | E7: 9.3 | F7: 6.55 | G7: =B7+MEDIAN(0,$B$4,Receita!$C$12)*C7+MEDIAN(0,$B$4-Receita!$C$12,Receita!$C$13-Receita!$C$12)*D7+MEDIAN(0,$B$4-Receita!$C$13,Receita!$C$14-Receita!$C$13)*E7+MAX(0,$B$4-Receita!$C$14)*F7 | H7: =G7*12 | I7: =IF($G$7=0,"",G7/$G$7-1)
A8: Base R$ 2.500 | B8: 2500 | C8: 9 | D8: 7 | E8: 5 | F8: 3 | G8: =B8+MEDIAN(0,$B$4,Receita!$C$12)*C8+MEDIAN(0,$B$4-Receita!$C$12,Receita!$C$13-Receita!$C$12)*D8+MEDIAN(0,$B$4-Receita!$C$13,Receita!$C$14-Receita!$C$13)*E8+MAX(0,$B$4-Receita!$C$14)*F8 | H8: =G8*12 | I8: =IF($G$7=0,"",G8/$G$7-1)
A9: Base R$ 3.500 | B9: 3500 | C9: 9 | D9: 7 | E9: 5 | F9: 3 | G9: =B9+MEDIAN(0,$B$4,Receita!$C$12)*C9+MEDIAN(0,$B$4-Receita!$C$12,Receita!$C$13-Receita!$C$12)*D9+MEDIAN(0,$B$4-Receita!$C$13,Receita!$C$14-Receita!$C$13)*E9+MAX(0,$B$4-Receita!$C$14)*F9 | H9: =G9*12 | I9: =IF($G$7=0,"",G9/$G$7-1)
A10: Faixas +25% | B10: 1200 | C10: 11.25 | D10: 8.75 | E10: 6.25 | F10: 3.75 | G10: =B10+MEDIAN(0,$B$4,Receita!$C$12)*C10+MEDIAN(0,$B$4-Receita!$C$12,Receita!$C$13-Receita!$C$12)*D10+MEDIAN(0,$B$4-Receita!$C$13,Receita!$C$14-Receita!$C$13)*E10+MAX(0,$B$4-Receita!$C$14)*F10 | H10: =G10*12 | I10: =IF($G$7=0,"",G10/$G$7-1)
A11: Faixas +40% | B11: 1200 | C11: 12.6 | D11: 9.8 | E11: 7 | F11: 4.2 | G11: =B11+MEDIAN(0,$B$4,Receita!$C$12)*C11+MEDIAN(0,$B$4-Receita!$C$12,Receita!$C$13-Receita!$C$12)*D11+MEDIAN(0,$B$4-Receita!$C$13,Receita!$C$14-Receita!$C$13)*E11+MAX(0,$B$4-Receita!$C$14)*F11 | H11: =G11*12 | I11: =IF($G$7=0,"",G11/$G$7-1)
A12: Base 2.500 + faixas +25% | B12: 2500 | C12: 11.25 | D12: 8.75 | E12: 6.25 | F12: 3.75 | G12: =B12+MEDIAN(0,$B$4,Receita!$C$12)*C12+MEDIAN(0,$B$4-Receita!$C$12,Receita!$C$13-Receita!$C$12)*D12+MEDIAN(0,$B$4-Receita!$C$13,Receita!$C$14-Receita!$C$13)*E12+MAX(0,$B$4-Receita!$C$14)*F12 | H12: =G12*12 | I12: =IF($G$7=0,"",G12/$G$7-1)
A15: A implantação não está aqui de propósito: ela é cobrança única e não muda a recorrência. Some na aba Receita, célula B17.

Sheet Concorrência
A1: Concorrência — preencher com cotações reais
A2: Nada aqui foi estimado. Preencha as células escuras com valores de propostas, tabelas públicas ou cotações recebidas — e anote a fonte e a data, porque preço sem procedência não sustenta argumento em reunião.
A4: Referência FROID (vem da aba Receita)
A5: Efetivo simulado | B5: =Receita!B5
A6: Anual FROID (com desconto) | B6: =Receita!B31
A7: Implantação FROID | B7: =Receita!B17
A8: Ano 1 FROID (anual + implantação) | B8: =Receita!B32
A9: Campanhas/ano FROID | B9: =Receita!B35
A10: Cotações
A11: Preencha “Mensal recorrente” OU “Por campanha”, conforme o modelo da cotação. Se os dois estiverem preenchidos, o cálculo usa o mensal. “Campanhas/ano” em branco assume o mesmo número do FROID, para que a comparação seja sobre o mesmo ciclo.
A12: Concorrente | B12: Modelo de cobrança | C12: Efetivo da cotação | D12: Implantação (única) | E12: Mensal recorrente | F12: Por campanha | G12: Campanhas/ano incluídas | H12: Prazo de entrega (dias) | I12: Fonte e data da informação
A20: Comparação — calculada a partir do que for preenchido
A21: Concorrente | B21: Anual do concorrente | C21: Ano 1 do concorrente | D21: Por trabalhador / ano | E21: Por campanha | F21: Ano 1 vs FROID (R$) | G21: Ano 1 vs FROID (%) | H21: FROID está…
A22: =IF(A13="","",A13) | B22: =IF(AND(E13="",F13=""),"",IF(E13<>"",E13*12,F13*IF(G13="",$B$9,G13))) | C22: =IF(B22="","",B22+IF(D13="",0,D13)) | D22: =IF(OR(B22="",C13="",C13=0),"",B22/C13) | E22: =IF(B22="","",B22/IF(G13="",$B$9,G13)) | F22: =IF(C22="","",$B$8-C22) | G22: =IF(OR(C22="",C22=0),"",$B$8/C22-1) | H22: =IF(G22="","",IF(G22>0.05,"mais caro",IF(G22<-0.05,"mais barato","equivalente")))
A23: =IF(A14="","",A14) | B23: =IF(AND(E14="",F14=""),"",IF(E14<>"",E14*12,F14*IF(G14="",$B$9,G14))) | C23: =IF(B23="","",B23+IF(D14="",0,D14)) | D23: =IF(OR(B23="",C14="",C14=0),"",B23/C14) | E23: =IF(B23="","",B23/IF(G14="",$B$9,G14)) | F23: =IF(C23="","",$B$8-C23) | G23: =IF(OR(C23="",C23=0),"",$B$8/C23-1) | H23: =IF(G23="","",IF(G23>0.05,"mais caro",IF(G23<-0.05,"mais barato","equivalente")))
A24: =IF(A15="","",A15) | B24: =IF(AND(E15="",F15=""),"",IF(E15<>"",E15*12,F15*IF(G15="",$B$9,G15))) | C24: =IF(B24="","",B24+IF(D15="",0,D15)) | D24: =IF(OR(B24="",C15="",C15=0),"",B24/C15) | E24: =IF(B24="","",B24/IF(G15="",$B$9,G15)) | F24: =IF(C24="","",$B$8-C24) | G24: =IF(OR(C24="",C24=0),"",$B$8/C24-1) | H24: =IF(G24="","",IF(G24>0.05,"mais caro",IF(G24<-0.05,"mais barato","equivalente")))
A25: =IF(A16="","",A16) | B25: =IF(AND(E16="",F16=""),"",IF(E16<>"",E16*12,F16*IF(G16="",$B$9,G16))) | C25: =IF(B25="","",B25+IF(D16="",0,D16)) | D25: =IF(OR(B25="",C16="",C16=0),"",B25/C16) | E25: =IF(B25="","",B25/IF(G16="",$B$9,G16)) | F25: =IF(C25="","",$B$8-C25) | G25: =IF(OR(C25="",C25=0),"",$B$8/C25-1) | H25: =IF(G25="","",IF(G25>0.05,"mais caro",IF(G25<-0.05,"mais barato","equivalente")))
A26: =IF(A17="","",A17) | B26: =IF(AND(E17="",F17=""),"",IF(E17<>"",E17*12,F17*IF(G17="",$B$9,G17))) | C26: =IF(B26="","",B26+IF(D17="",0,D17)) | D26: =IF(OR(B26="",C17="",C17=0),"",B26/C17) | E26: =IF(B26="","",B26/IF(G17="",$B$9,G17)) | F26: =IF(C26="","",$B$8-C26) | G26: =IF(OR(C26="",C26=0),"",$B$8/C26-1) | H26: =IF(G26="","",IF(G26>0.05,"mais caro",IF(G26<-0.05,"mais barato","equivalente")))
A27: =IF(A18="","",A18) | B27: =IF(AND(E18="",F18=""),"",IF(E18<>"",E18*12,F18*IF(G18="",$B$9,G18))) | C27: =IF(B27="","",B27+IF(D18="",0,D18)) | D27: =IF(OR(B27="",C18="",C18=0),"",B27/C18) | E27: =IF(B27="","",B27/IF(G18="",$B$9,G18)) | F27: =IF(C27="","",$B$8-C27) | G27: =IF(OR(C27="",C27=0),"",$B$8/C27-1) | H27: =IF(G27="","",IF(G27>0.05,"mais caro",IF(G27<-0.05,"mais barato","equivalente")))
A29: Cuidado ao comparar: quase nenhum concorrente entrega prova de eficácia antes/depois nem piso de anonimato. Preço menor por um escopo menor não é preço menor — é outro produto. A matriz abaixo existe para não deixar isso passar.
A31: O que cada um entrega (preencher: sim / não / parcial)
A32: Capacidade | B32: FROID | C32: Concorrente 1 | D32: Concorrente 2 | E32: Concorrente 3 | F32: Concorrente 4 | G32: Concorrente 5 | H32: Concorrente 6
A33: (nome da cotação) | C33: =IF(A13="","",A13) | D33: =IF(A14="","",A14) | E33: =IF(A15="","",A15) | F33: =IF(A16="","",A16) | G33: =IF(A17="","",A17) | H33: =IF(A18="","",A18)
A34: Inventário com os nove campos (1.5.7.3.2) | B34: sim
A35: AEP psicossocial | B35: sim
A36: Gradação por severidade × probabilidade (1.5.4.4.4) | B36: sim
A37: Probabilidade desconta eficácia medida (1.5.4.4.5.3) | B37: sim
A38: Prova de eficácia antes/depois, setor contra si mesmo | B38: sim
A39: Medida ineficaz não reduz risco no papel (1.5.5.3.2.1) | B39: sim
A40: Piso de anonimato por recorte | B40: sim
A41: Resultado só após encerrar a campanha | B41: sim
A42: Recusa abrir campanha sem canal de apoio | B42: sim
A43: Critérios de gradação alinhados ao PGR da empresa | B43: sim
A44: Guarda do histórico por 20 anos (1.5.7.3.3.1) | B44: sim
A45: Painel próprio, sem planilha intermediária | B45: sim
... A47: Não entrega resposta individual a ninguém | B47: sim
A49: A coluna FROID reflete o que está implementado no produto hoje. Se alguma linha deixar de ser verdade, corrija aqui antes de usar a matriz com um cliente.
