Workbook

Sheet Guia
A1: FROID PSIQUE | Custo por crédito de atendimento
A2: 24/09/2026 | Estudo gerencial. Não aprova nem altera preços ou configurações Stripe.
A5: Etapa | B5: Como utilizar
A6: Unidade | B6: Um crédito de atendimento corresponde a um atendimento na regra atual. Sessão continua sendo o registro clínico; duração e regra de consumo não foram alteradas.
A7: Preenchimento | B7: Amarelo: entrada. Azul: referência. Verde: fórmula. Vazio = não apurado. Zero somente quando houver confirmação de custo/consumo nulo.
A8: Ordem | B8: Preencha Premissas, Fixos, Variáveis e IA; consulte Resultado, Pacotes e Cenários.
A9: Exclusões | B9: Não se aplica exige justificativa. Itens pendentes bloqueiam custo completo e preço mínimo, evitando que um subtotal pareça o total.
A10: Regime | B10: Modelo mensal de equilíbrio: receitas de créditos pagos utilizados, uso integral dos pacotes e taxas de compra rateadas. Não é fluxo de caixa de vendas antecipadas.
A11: Gratuitos | B11: Atendimentos gratuitos também consomem APIs e estrutura. O custo deles é suportado pelos créditos pagos. Desconto de pioneiro encerrado; cortesia não foi cancelada.
A12: Não duplicar | B12: Cada gasto aparece uma vez. APIs são calculadas em IA. Suporte pode ser folha fixa OU variável por atendimento; não repetir horas nem faturas.
A13: Rateio | B13: Infra compartilhada com NR-1, site e desenvolvimento exige critério documentado. Não atribuir tudo ao Psique sem apuração.
A14: APIs | B14: Use minutos efetivamente enviados de paciente e profissional, incluindo reenvios. Tokens incluem prompts, histórico, resumos, análises, relatórios, consultas e fallback. max_tokens não é consumo.
A15: Histórico | B15: Armazenamento e backup incluem o acervo acumulado. Use faturas ou projeções documentadas; não presumir exclusão de registros após acabar o crédito.
A16: Câmbio e impostos | B16: Informe câmbio efetivo com IOF/spread. A contabilidade deve apurar a alíquota de tributos. Nenhum regime tributário foi presumido.
... A22: Fonte | B22: Modelos em produção conferidos em 24/09/2026: gpt-4o-mini, gpt-4o-transcribe, gemini-1.5-pro. Não houve acesso a extratos de fornecedores nem a dados clínicos.

Sheet Premissas
A1: ENTRADAS | Volume, preço e cobrança
A2: Valores confirmados ou hipóteses identificadas na fonte. Digite percentuais com %. Custos ausentes não são zero.
A5: Premissa | B5: Valor | C5: Unidade | D5: Fonte / observação
A6: Créditos pagos utilizados no mês | C6: créditos | D6: Base de rateio: maior que zero.
A7: Créditos gratuitos utilizados no mês | C7: créditos | D7: Zero somente se não houver uso gratuito.
A8: Atendimentos totais no mês | B8: =IF(COUNT(B6:B7)=2,SUM(B6:B7),"Sem Capacidade de Apuração") -> Sem Capacidade de Apuração | C8: atendimentos | D8: Pagos + gratuitos.
A9: Duração média observada | C9: minutos | D9: Contexto: não substitui minutos faturados de transcrição.
A10: Créditos por pacote de referência | C10: créditos/pacote | D10: Para mix, média comprovada de créditos por pagamento.
A11: Preço a avaliar por crédito | C11: BRL/crédito | D11: Sua decisão comercial, ainda não aprovada/publicada.
A12: Margem operacional desejada | C12: % receita | D12: Margem sobre receita, não markup.
A13: USD para BRL efetivo | C13: BRL/USD | D13: Inclua spread e encargos cambiais; não duplicar em outra linha.
A14: EUR para BRL efetivo | C14: BRL/EUR | D14: Necessário apenas para faturas em EUR.
A15: Tributos efetivos sobre faturamento | C15: % receita | D15: Apurar com a contabilidade.
A16: Comissões variáveis | C16: % receita | D16: Não duplicar valores lançados em Fixos/Variáveis.
A17: Perdas e reembolsos líquidos | C17: % receita | D17: Provisão informada; tarifas de contestação ficam em Fixos.
A18: Tarifa percentual do pagamento | C18: % receita | D18: Contratada ou média ponderada: consulte Referências.
A19: Tarifa fixa por pagamento | C19: BRL/transação | D19: Por pacote comprado, não por crédito.
A20: Outras tarifas percentuais | C20: % receita | D20: Parcelamento, Billing, conversão ou adicionais não incluídos acima.
A21: Desconto de pioneiro vigente | B21: 0 | C21: % | D21: 0% por determinação do proprietário em 24/09/2026.

Sheet Referencias
A1: REFERÊNCIAS | Tarifas públicas
A2: Consulta em 24/09/2026. Não substitui contrato/fatura. Gemini configurado não localizado na tabela atual: tarifa pendente.
A5: Serviço | B5: Tarifa | C5: Unidade | D5: Fonte | E5: Observação
A6: gpt-4o-transcribe | B6: 0.006 | C6: USD/minuto | D6: https://developers.openai.com/api/docs/pricing | E6: Estimativa oficial por minuto; conciliar com usage/fatura.
A7: gpt-4o-mini entrada | B7: 0.15 | C7: USD/1M tokens | D7: https://developers.openai.com/api/docs/models/gpt-4o-mini | E7: Tarifa padrão sem cache; não usar preço Batch.
A8: gpt-4o-mini cache | B8: 0.075 | C8: USD/1M tokens | D8: https://developers.openai.com/api/docs/models/gpt-4o-mini | E8: Só tokens cobrados com cache.
A9: gpt-4o-mini saída | B9: 0.6 | C9: USD/1M tokens | D9: https://developers.openai.com/api/docs/models/gpt-4o-mini | E9: Uso medido, não limite de geração.
A10: text-embedding-3-small | B10: 0.02 | C10: USD/1M tokens | D10: https://developers.openai.com/api/docs/models/text-embedding-3-small | E10: Confirmar consultas e reindexações atribuíveis ao Psique.
A11: Gemini entrada (gemini-1.5-pro) | C11: USD/1M tokens | D11: https://ai.google.dev/gemini-api/docs/pricing | E11: Tarifa atual não localizada para modelo configurado. Confirmar uso/modelo/fatura.
A12: Gemini saída (gemini-1.5-pro) | C12: USD/1M tokens | D12: https://ai.google.dev/gemini-api/docs/pricing | E12: Ausência não significa custo zero; pode haver fallback OpenAI.
A13: Stripe cartão nacional — percentual | B13: 0.0399 | C13: % transação | D13: https://stripe.com/br/pricing | E13: Confirmar tarifa contratada.
A14: Stripe cartão nacional — fixa | B14: 0.39 | C14: BRL/transação | D14: https://stripe.com/br/pricing | E14: Distribuir pelos créditos comprados.
A15: Stripe internacional — adicional | B15: 0.02 | C15: % transação | D15: https://stripe.com/br/pricing | E15: Adicional à tarifa nacional; verificar condições de conversão.
A16: Stripe Pix | B16: 0.0119 | C16: % transação | D16: https://stripe.com/br/pricing | E16: Por convite segundo página consultada; não assume habilitação.
A17: Stripe boleto | B17: 3.45 | C17: BRL/boleto pago | D17: https://stripe.com/br/pricing | E17: Alternativa; não somar ao cartão na mesma venda.
A18: Stripe contestação recebida | B18: 55 | C18: BRL/evento | D18: https://stripe.com/br/pricing | E18: Não presumir ocorrência.
A19: Stripe refutação manual | B19: 55 | C19: BRL/evento | D19: https://stripe.com/br/pricing | E19: Tarifa devolvida em disputas ganhas; registrar custo líquido.
A20: Catálogo comercial | B20: Confirmado | C20: código | D20: froid-server/subscriptions.py | E20: MASTER diverge do site; ver Pacotes.
A21: Infra compartilhada | B21: Ratear | C21: código | D21: docker-compose.yml | E21: Não alocar NR-1 e desenvolvimento integralmente ao Psique.

Sheet IA
A1: APIs | Custo por atendimento
A2: Quantidade média por atendimento, incluindo gratuitos. Some todo uso pago; entrada com cache não pode ser contada novamente sem cache.
A5: Componente | B5: Quantidade | C5: Unidade | D5: Tarifa USD | E5: Divisor | F5: USD/atendimento | G5: BRL/atendimento | H5: Fonte da medição
A6: Transcrição paciente | C6: minutos | D6: =IF(ISNUMBER(Referencias!B6),Referencias!B6,"Sem Capacidade de Apuração") -> 0.006 | E6: 1 | F6: =IF(COUNT(B6)<>1,"Sem Capacidade de Apuração",IF(B6=0,0,IF(COUNT(D6)=1,B6*D6/E6,"Sem Capacidade de Apuração"))) -> Sem Capacidade de Apuração | G6: =IF(ISNUMBER(F6),IF(F6=0,0,IF(AND(ISNUMBER(Premissas!B13),Premissas!B13>0),F6*Premissas!B13,"Sem Capacidade de Apuração")),"Sem Capacidade de Apuração") -> Sem Capacidade de Apuração
A7: Transcrição profissional | C7: minutos | D7: =IF(ISNUMBER(Referencias!B6),Referencias!B6,"Sem Capacidade de Apuração") -> 0.006 | E7: 1 | F7: =IF(COUNT(B7)<>1,"Sem Capacidade de Apuração",IF(B7=0,0,IF(COUNT(D7)=1,B7*D7/E7,"Sem Capacidade de Apuração"))) -> Sem Capacidade de Apuração | G7: =IF(ISNUMBER(F7),IF(F7=0,0,IF(AND(ISNUMBER(Premissas!B13),Premissas!B13>0),F7*Premissas!B13,"Sem Capacidade de Apuração")),"Sem Capacidade de Apuração") -> Sem Capacidade de Apuração
A8: Texto OpenAI — entrada sem cache | C8: tokens | D8: =IF(ISNUMBER(Referencias!B7),Referencias!B7,"Sem Capacidade de Apuração") -> 0.15 | E8: 1000000 | F8: =IF(COUNT(B8)<>1,"Sem Capacidade de Apuração",IF(B8=0,0,IF(COUNT(D8)=1,B8*D8/E8,"Sem Capacidade de Apuração"))) -> Sem Capacidade de Apuração | G8: =IF(ISNUMBER(F8),IF(F8=0,0,IF(AND(ISNUMBER(Premissas!B13),Premissas!B13>0),F8*Premissas!B13,"Sem Capacidade de Apuração")),"Sem Capacidade de Apuração") -> Sem Capacidade de Apuração
A9: Texto OpenAI — entrada cache | C9: tokens | D9: =IF(ISNUMBER(Referencias!B8),Referencias!B8,"Sem Capacidade de Apuração") -> 0.075 | E9: 1000000 | F9: =IF(COUNT(B9)<>1,"Sem Capacidade de Apuração",IF(B9=0,0,IF(COUNT(D9)=1,B9*D9/E9,"Sem Capacidade de Apuração"))) -> Sem Capacidade de Apuração | G9: =IF(ISNUMBER(F9),IF(F9=0,0,IF(AND(ISNUMBER(Premissas!B13),Premissas!B13>0),F9*Premissas!B13,"Sem Capacidade de Apuração")),"Sem Capacidade de Apuração") -> Sem Capacidade de Apuração
A10: Texto OpenAI — saída | C10: tokens | D10: =IF(ISNUMBER(Referencias!B9),Referencias!B9,"Sem Capacidade de Apuração") -> 0.6 | E10: 1000000 | F10: =IF(COUNT(B10)<>1,"Sem Capacidade de Apuração",IF(B10=0,0,IF(COUNT(D10)=1,B10*D10/E10,"Sem Capacidade de Apuração"))) -> Sem Capacidade de Apuração | G10: =IF(ISNUMBER(F10),IF(F10=0,0,IF(AND(ISNUMBER(Premissas!B13),Premissas!B13>0),F10*Premissas!B13,"Sem Capacidade de Apuração")),"Sem Capacidade de Apuração") -> Sem Capacidade de Apuração
A11: Embeddings Psique | C11: tokens | D11: =IF(ISNUMBER(Referencias!B10),Referencias!B10,"Sem Capacidade de Apuração") -> 0.02 | E11: 1000000 | F11: =IF(COUNT(B11)<>1,"Sem Capacidade de Apuração",IF(B11=0,0,IF(COUNT(D11)=1,B11*D11/E11,"Sem Capacidade de Apuração"))) -> Sem Capacidade de Apuração | G11: =IF(ISNUMBER(F11),IF(F11=0,0,IF(AND(ISNUMBER(Premissas!B13),Premissas!B13>0),F11*Premissas!B13,"Sem Capacidade de Apuração")),"Sem Capacidade de Apuração") -> Sem Capacidade de Apuração
A12: Gemini — entrada | C12: tokens | D12: =IF(ISNUMBER(Referencias!B11),Referencias!B11,"Sem Capacidade de Apuração") -> Sem Capacidade de Apuração | E12: 1000000 | F12: =IF(COUNT(B12)<>1,"Sem Capacidade de Apuração",IF(B12=0,0,IF(COUNT(D12)=1,B12*D12/E12,"Sem Capacidade de Apuração"))) -> Sem Capacidade de Apuração | G12: =IF(ISNUMBER(F12),IF(F12=0,0,IF(AND(ISNUMBER(Premissas!B13),Premissas!B13>0),F12*Premissas!B13,"Sem Capacidade de Apuração")),"Sem Capacidade de Apuração") -> Sem Capacidade de Apuração
A13: Gemini — saída | C13: tokens | D13: =IF(ISNUMBER(Referencias!B12),Referencias!B12,"Sem Capacidade de Apuração") -> Sem Capacidade de Apuração | E13: 1000000 | F13: =IF(COUNT(B13)<>1,"Sem Capacidade de Apuração",IF(B13=0,0,IF(COUNT(D13)=1,B13*D13/E13,"Sem Capacidade de Apuração"))) -> Sem Capacidade de Apuração | G13: =IF(ISNUMBER(F13),IF(F13=0,0,IF(AND(ISNUMBER(Premissas!B13),Premissas!B13>0),F13*Premissas!B13,"Sem Capacidade de Apuração")),"Sem Capacidade de Apuração") -> Sem Capacidade de Apuração
A14: Outras APIs / conciliação comprovada | C14: unidades | E14: 1 | F14: =IF(COUNT(B14)<>1,"Sem Capacidade de Apuração",IF(B14=0,0,IF(COUNT(D14)=1,B14*D14/E14,"Sem Capacidade de Apuração"))) -> Sem Capacidade de Apuração | G14: =IF(ISNUMBER(F14),IF(F14=0,0,IF(AND(ISNUMBER(Premissas!B13),Premissas!B13>0),F14*Premissas!B13,"Sem Capacidade de Apuração")),"Sem Capacidade de Apuração") -> Sem Capacidade de Apuração
A16: TOTAL IA POR ATENDIMENTO | G16: =IF(COUNT(G6:G14)=9,SUM(G6:G14),"Sem Capacidade de Apuração") -> Sem Capacidade de Apuração
A18: PENDÊNCIAS | G18: =9-COUNT(G6:G14) -> 9

Sheet Fixos
A1: CUSTOS MENSAIS | Faturas e estrutura
A2: Classifique todas as linhas. Não se aplica exige justificativa. Valor 0 exige confirmação de ausência de gasto. Documente o rateio.
A5: Item | B5: Tratamento | C5: Valor da fatura | D5: Moeda | E5: Rateio Psique | F5: BRL/mês | G5: Fonte / justificativa | H5: Situação
A6: Servidor Hetzner / computação | B6: Pendente | F6: =IF(B6="Não se aplica",IF(G6<>"",0,"Sem Capacidade de Apuração"),IF(AND(B6="Informado",COUNT(C6,E6)=2,C6>=0,E6>=0,E6<=1,G6<>""),IF(ISNUMBER(IF(D6="BRL",1,IF(D6="USD",IF(AND(ISNUMBER(Premissas!B13),Premissas!B13>0),Premissas!B13,"Sem Capacidade de Apuração"),IF(D6="EUR",IF(AND(ISNUMBER(Premissas!B14),Premissas!B14>0),Premissas!B14,"Sem Capacidade de Apuração"),"Sem Capacidade de Apuração")))),C6*E6*IF(D6="BRL",1,IF(D6="USD",IF(AND(ISNUMBER(Premissas!B13),Premissas!B13>0),Premissas!B13,"Sem Capacidade de Apuração"),IF(D6="EUR",IF(AND(ISNUMBER(Premissas!B14),Premissas!B14>0),Premissas!B14,"Sem Capacidade de Apuração"),"Sem Capacidade de Apuração"))),"Sem Capacidade de Apuração"),"Sem Capacidade de Apuração")) -> Sem Capacidade de Apuração | H6: =IF(ISNUMBER(F6),"OK","Pendente") -> Pendente
A7: Banco de dados / volume adicional | B7: Pendente | F7: =IF(B7="Não se aplica",IF(G7<>"",0,"Sem Capacidade de Apuração"),IF(AND(B7="Informado",COUNT(C7,E7)=2,C7>=0,E7>=0,E7<=1,G7<>""),IF(ISNUMBER(IF(D7="BRL",1,IF(D7="USD",IF(AND(ISNUMBER(Premissas!B13),Premissas!B13>0),Premissas!B13,"Sem Capacidade de Apuração"),IF(D7="EUR",IF(AND(ISNUMBER(Premissas!B14),Premissas!B14>0),Premissas!B14,"Sem Capacidade de Apuração"),"Sem Capacidade de Apuração")))),C7*E7*IF(D7="BRL",1,IF(D7="USD",IF(AND(ISNUMBER(Premissas!B13),Premissas!B13>0),Premissas!B13,"Sem Capacidade de Apuração"),IF(D7="EUR",IF(AND(ISNUMBER(Premissas!B14),Premissas!B14>0),Premissas!B14,"Sem Capacidade de Apuração"),"Sem Capacidade de Apuração"))),"Sem Capacidade de Apuração"),"Sem Capacidade de Apuração")) -> Sem Capacidade de Apuração | H7: =IF(ISNUMBER(F7),"OK","Pendente") -> Pendente
A8: Backups / snapshots / recuperação | B8: Pendente | F8: =IF(B8="Não se aplica",IF(G8<>"",0,"Sem Capacidade de Apuração"),IF(AND(B8="Informado",COUNT(C8,E8)=2,C8>=0,E8>=0,E8<=1,G8<>""),IF(ISNUMBER(IF(D8="BRL",1,IF(D8="USD",IF(AND(ISNUMBER(Premissas!B13),Premissas!B13>0),Premissas!B13,"Sem Capacidade de Apuração"),IF(D8="EUR",IF(AND(ISNUMBER(Premissas!B14),Premissas!B14>0),Premissas!B14,"Sem Capacidade de Apuração"),"Sem Capacidade de Apuração")))),C8*E8*IF(D8="BRL",1,IF(D8="USD",IF(AND(ISNUMBER(Premissas!B13),Premissas!B13>0),Premissas!B13,"Sem Capacidade de Apuração"),IF(D8="EUR",IF(AND(ISNUMBER(Premissas!B14),Premissas!B14>0),Premissas!B14,"Sem Capacidade de Apuração"),"Sem Capacidade de Apuração"))),"Sem Capacidade de Apuração"),"Sem Capacidade de Apuração")) -> Sem Capacidade de Apuração | H8: =IF(ISNUMBER(F8),"OK","Pendente") -> Pendente
A9: Armazenamento de históricos e documentos | B9: Pendente | F9: =IF(B9="Não se aplica",IF(G9<>"",0,"Sem Capacidade de Apuração"),IF(AND(B9="Informado",COUNT(C9,E9)=2,C9>=0,E9>=0,E9<=1,G9<>""),IF(ISNUMBER(IF(D9="BRL",1,IF(D9="USD",IF(AND(ISNUMBER(Premissas!B13),Premissas!B13>0),Premissas!B13,"Sem Capacidade de Apuração"),IF(D9="EUR",IF(AND(ISNUMBER(Premissas!B14),Premissas!B14>0),Premissas!B14,"Sem Capacidade de Apuração"),"Sem Capacidade de Apuração")))),C9*E9*IF(D9="BRL",1,IF(D9="USD",IF(AND(ISNUMBER(Premissas!B13),Premissas!B13>0),Premissas!B13,"Sem Capacidade de Apuração"),IF(D9="EUR",IF(AND(ISNUMBER(Premissas!B14),Premissas!B14>0),Premissas!B14,"Sem Capacidade de Apuração"),"Sem Capacidade de Apuração"))),"Sem Capacidade de Apuração"),"Sem Capacidade de Apuração")) -> Sem Capacidade de Apuração | H9: =IF(ISNUMBER(F9),"OK","Pendente") -> Pendente
A10: TURN / conectividade / tráfego contratado | B10: Pendente | F10: =IF(B10="Não se aplica",IF(G10<>"",0,"Sem Capacidade de Apuração"),IF(AND(B10="Informado",COUNT(C10,E10)=2,C10>=0,E10>=0,E10<=1,G10<>""),IF(ISNUMBER(IF(D10="BRL",1,IF(D10="USD",IF(AND(ISNUMBER(Premissas!B13),Premissas!B13>0),Premissas!B13,"Sem Capacidade de Apuração"),IF(D10="EUR",IF(AND(ISNUMBER(Premissas!B14),Premissas!B14>0),Premissas!B14,"Sem Capacidade de Apuração"),"Sem Capacidade de Apuração")))),C10*E10*IF(D10="BRL",1,IF(D10="USD",IF(AND(ISNUMBER(Premissas!B13),Premissas!B13>0),Premissas!B13,"Sem Capacidade de Apuração"),IF(D10="EUR",IF(AND(ISNUMBER(Premissas!B14),Premissas!B14>0),Premissas!B14,"Sem Capacidade de Apuração"),"Sem Capacidade de Apuração"))),"Sem Capacidade de Apuração"),"Sem Capacidade de Apuração")) -> Sem Capacidade de Apuração | H10: =IF(ISNUMBER(F10),"OK","Pendente") -> Pendente
A11: CDN / DNS / proteção de borda | B11: Pendente | F11: =IF(B11="Não se aplica",IF(G11<>"",0,"Sem Capacidade de Apuração"),IF(AND(B11="Informado",COUNT(C11,E11)=2,C11>=0,E11>=0,E11<=1,G11<>""),IF(ISNUMBER(IF(D11="BRL",1,IF(D11="USD",IF(AND(ISNUMBER(Premissas!B13),Premissas!B13>0),Premissas!B13,"Sem Capacidade de Apuração"),IF(D11="EUR",IF(AND(ISNUMBER(Premissas!B14),Premissas!B14>0),Premissas!B14,"Sem Capacidade de Apuração"),"Sem Capacidade de Apuração")))),C11*E11*IF(D11="BRL",1,IF(D11="USD",IF(AND(ISNUMBER(Premissas!B13),Premissas!B13>0),Premissas!B13,"Sem Capacidade de Apuração"),IF(D11="EUR",IF(AND(ISNUMBER(Premissas!B14),Premissas!B14>0),Premissas!B14,"Sem Capacidade de Apuração"),"Sem Capacidade de Apuração"))),"Sem Capacidade de Apuração"),"Sem Capacidade de Apuração")) -> Sem Capacidade de Apuração | H11: =IF(ISNUMBER(F11),"OK","Pendente") -> Pendente
A12: Domínio (mensalizar custo anual) | B12: Pendente | F12: =IF(B12="Não se aplica",IF(G12<>"",0,"Sem Capacidade de Apuração"),IF(AND(B12="Informado",COUNT(C12,E12)=2,C12>=0,E12>=0,E12<=1,G12<>""),IF(ISNUMBER(IF(D12="BRL",1,IF(D12="USD",IF(AND(ISNUMBER(Premissas!B13),Premissas!B13>0),Premissas!B13,"Sem Capacidade de Apuração"),IF(D12="EUR",IF(AND(ISNUMBER(Premissas!B14),Premissas!B14>0),Premissas!B14,"Sem Capacidade de Apuração"),"Sem Capacidade de Apuração")))),C12*E12*IF(D12="BRL",1,IF(D12="USD",IF(AND(ISNUMBER(Premissas!B13),Premissas!B13>0),Premissas!B13,"Sem Capacidade de Apuração"),IF(D12="EUR",IF(AND(ISNUMBER(Premissas!B14),Premissas!B14>0),Premissas!B14,"Sem Capacidade de Apuração"),"Sem Capacidade de Apuração"))),"Sem Capacidade de Apuração"),"Sem Capacidade de Apuração")) -> Sem Capacidade de Apuração | H12: =IF(ISNUMBER(F12),"OK","Pendente") -> Pendente
A13: E-mail transacional / SMTP | B13: Pendente | F13: =IF(B13="Não se aplica",IF(G13<>"",0,"Sem Capacidade de Apuração"),IF(AND(B13="Informado",COUNT(C13,E13)=2,C13>=0,E13>=0,E13<=1,G13<>""),IF(ISNUMBER(IF(D13="BRL",1,IF(D13="USD",IF(AND(ISNUMBER(Premissas!B13),Premissas!B13>0),Premissas!B13,"Sem Capacidade de Apuração"),IF(D13="EUR",IF(AND(ISNUMBER(Premissas!B14),Premissas!B14>0),Premissas!B14,"Sem Capacidade de Apuração"),"Sem Capacidade de Apuração")))),C13*E13*IF(D13="BRL",1,IF(D13="USD",IF(AND(ISNUMBER(Premissas!B13),Premissas!B13>0),Premissas!B13,"Sem Capacidade de Apuração"),IF(D13="EUR",IF(AND(ISNUMBER(Premissas!B14),Premissas!B14>0),Premissas!B14,"Sem Capacidade de Apuração"),"Sem Capacidade de Apuração"))),"Sem Capacidade de Apuração"),"Sem Capacidade de Apuração")) -> Sem Capacidade de Apuração | H13: =IF(ISNUMBER(F13),"OK","Pendente") -> Pendente
A14: Monitoramento / logs / alertas | B14: Pendente | F14: =IF(B14="Não se aplica",IF(G14<>"",0,"Sem Capacidade de Apuração"),IF(AND(B14="Informado",COUNT(C14,E14)=2,C14>=0,E14>=0,E14<=1,G14<>""),IF(ISNUMBER(IF(D14="BRL",1,IF(D14="USD",IF(AND(ISNUMBER(Premissas!B13),Premissas!B13>0),Premissas!B13,"Sem Capacidade de Apuração"),IF(D14="EUR",IF(AND(ISNUMBER(Premissas!B14),Premissas!B14>0),Premissas!B14,"Sem Capacidade de Apuração"),"Sem Capacidade de Apuração")))),C14*E14*IF(D14="BRL",1,IF(D14="USD",IF(AND(ISNUMBER(Premissas!B13),Premissas!B13>0),Premissas!B13,"Sem Capacidade de Apuração"),IF(D14="EUR",IF(AND(ISNUMBER(Premissas!B14),Premissas!B14>0),Premissas!B14,"Sem Capacidade de Apuração"),"Sem Capacidade de Apuração"))),"Sem Capacidade de Apuração"),"Sem Capacidade de Apuração")) -> Sem Capacidade de Apuração | H14: =IF(ISNUMBER(F14),"OK","Pendente") -> Pendente
A15: Segurança / auditoria / testes | B15: Pendente | F15: =IF(B15="Não se aplica",IF(G15<>"",0,"Sem Capacidade de Apuração"),IF(AND(B15="Informado",COUNT(C15,E15)=2,C15>=0,E15>=0,E15<=1,G15<>""),IF(ISNUMBER(IF(D15="BRL",1,IF(D15="USD",IF(AND(ISNUMBER(Premissas!B13),Premissas!B13>0),Premissas!B13,"Sem Capacidade de Apuração"),IF(D15="EUR",IF(AND(ISNUMBER(Premissas!B14),Premissas!B14>0),Premissas!B14,"Sem Capacidade de Apuração"),"Sem Capacidade de Apuração")))),C15*E15*IF(D15="BRL",1,IF(D15="USD",IF(AND(ISNUMBER(Premissas!B13),Premissas!B13>0),Premissas!B13,"Sem Capacidade de Apuração"),IF(D15="EUR",IF(AND(ISNUMBER(Premissas!B14),Premissas!B14>0),Premissas!B14,"Sem Capacidade de Apuração"),"Sem Capacidade de Apuração"))),"Sem Capacidade de Apuração"),"Sem Capacidade de Apuração")) -> Sem Capacidade de Apuração | H15: =IF(ISNUMBER(F15),"OK","Pendente") -> Pendente
A16: Suporte fixo / atendimento ao cliente | B16: Pendente | F16: =IF(B16="Não se aplica",IF(G16<>"",0,"Sem Capacidade de Apuração"),IF(AND(B16="Informado",COUNT(C16,E16)=2,C16>=0,E16>=0,E16<=1,G16<>""),IF(ISNUMBER(IF(D16="BRL",1,IF(D16="USD",IF(AND(ISNUMBER(Premissas!B13),Premissas!B13>0),Premissas!B13,"Sem Capacidade de Apuração"),IF(D16="EUR",IF(AND(ISNUMBER(Premissas!B14),Premissas!B14>0),Premissas!B14,"Sem Capacidade de Apuração"),"Sem Capacidade de Apuração")))),C16*E16*IF(D16="BRL",1,IF(D16="USD",IF(AND(ISNUMBER(Premissas!B13),Premissas!B13>0),Premissas!B13,"Sem Capacidade de Apuração"),IF(D16="EUR",IF(AND(ISNUMBER(Premissas!B14),Premissas!B14>0),Premissas!B14,"Sem Capacidade de Apuração"),"Sem Capacidade de Apuração"))),"Sem Capacidade de Apuração"),"Sem Capacidade de Apuração")) -> Sem Capacidade de Apuração | H16: =IF(ISNUMBER(F16),"OK","Pendente") -> Pendente
A17: Manutenção / desenvolvimento recorrente | B17: Pendente | F17: =IF(B17="Não se aplica",IF(G17<>"",0,"Sem Capacidade de Apuração"),IF(AND(B17="Informado",COUNT(C17,E17)=2,C17>=0,E17>=0,E17<=1,G17<>""),IF(ISNUMBER(IF(D17="BRL",1,IF(D17="USD",IF(AND(ISNUMBER(Premissas!B13),Premissas!B13>0),Premissas!B13,"Sem Capacidade de Apuração"),IF(D17="EUR",IF(AND(ISNUMBER(Premissas!B14),Premissas!B14>0),Premissas!B14,"Sem Capacidade de Apuração"),"Sem Capacidade de Apuração")))),C17*E17*IF(D17="BRL",1,IF(D17="USD",IF(AND(ISNUMBER(Premissas!B13),Premissas!B13>0),Premissas!B13,"Sem Capacidade de Apuração"),IF(D17="EUR",IF(AND(ISNUMBER(Premissas!B14),Premissas!B14>0),Premissas!B14,"Sem Capacidade de Apuração"),"Sem Capacidade de Apuração"))),"Sem Capacidade de Apuração"),"Sem Capacidade de Apuração")) -> Sem Capacidade de Apuração | H17: =IF(ISNUMBER(F17),"OK","Pendente") -> Pendente
A18: Pró-labore e encargos dos sócios | B18: Pendente | F18: =IF(B18="Não se aplica",IF(G18<>"",0,"Sem Capacidade de Apuração"),IF(AND(B18="Informado",COUNT(C18,E18)=2,C18>=0,E18>=0,E18<=1,G18<>""),IF(ISNUMBER(IF(D18="BRL",1,IF(D18="USD",IF(AND(ISNUMBER(Premissas!B13),Premissas!B13>0),Premissas!B13,"Sem Capacidade de Apuração"),IF(D18="EUR",IF(AND(ISNUMBER(Premissas!B14),Premissas!B14>0),Premissas!B14,"Sem Capacidade de Apuração"),"Sem Capacidade de Apuração")))),C18*E18*IF(D18="BRL",1,IF(D18="USD",IF(AND(ISNUMBER(Premissas!B13),Premissas!B13>0),Premissas!B13,"Sem Capacidade de Apuração"),IF(D18="EUR",IF(AND(ISNUMBER(Premissas!B14),Premissas!B14>0),Premissas!B14,"Sem Capacidade de Apuração"),"Sem Capacidade de Apuração"))),"Sem Capacidade de Apuração"),"Sem Capacidade de Apuração")) -> Sem Capacidade de Apuração | H18: =IF(ISNUMBER(F18),"OK","Pendente") -> Pendente
A19: Equipe administrativa / encargos | B19: Pendente | F19: =IF(B19="Não se aplica",IF(G19<>"",0,"Sem Capacidade de Apuração"),IF(AND(B19="Informado",COUNT(C19,E19)=2,C19>=0,E19>=0,E19<=1,G19<>""),IF(ISNUMBER(IF(D19="BRL",1,IF(D19="USD",IF(AND(ISNUMBER(Premissas!B13),Premissas!B13>0),Premissas!B13,"Sem Capacidade de Apuração"),IF(D19="EUR",IF(AND(ISNUMBER(Premissas!B14),Premissas!B14>0),Premissas!B14,"Sem Capacidade de Apuração"),"Sem Capacidade de Apuração")))),C19*E19*IF(D19="BRL",1,IF(D19="USD",IF(AND(ISNUMBER(Premissas!B13),Premissas!B13>0),Premissas!B13,"Sem Capacidade de Apuração"),IF(D19="EUR",IF(AND(ISNUMBER(Premissas!B14),Premissas!B14>0),Premissas!B14,"Sem Capacidade de Apuração"),"Sem Capacidade de Apuração"))),"Sem Capacidade de Apuração"),"Sem Capacidade de Apuração")) -> Sem Capacidade de Apuração | H19: =IF(ISNUMBER(F19),"OK","Pendente") -> Pendente
A20: Equipe técnica / encargos | B20: Pendente | F20: =IF(B20="Não se aplica",IF(G20<>"",0,"Sem Capacidade de Apuração"),IF(AND(B20="Informado",COUNT(C20,E20)=2,C20>=0,E20>=0,E20<=1,G20<>""),IF(ISNUMBER(IF(D20="BRL",1,IF(D20="USD",IF(AND(ISNUMBER(Premissas!B13),Premissas!B13>0),Premissas!B13,"Sem Capacidade de Apuração"),IF(D20="EUR",IF(AND(ISNUMBER(Premissas!B14),Premissas!B14>0),Premissas!B14,"Sem Capacidade de Apuração"),"Sem Capacidade de Apuração")))),C20*E20*IF(D20="BRL",1,IF(D20="USD",IF(AND(ISNUMBER(Premissas!B13),Premissas!B13>0),Premissas!B13,"Sem Capacidade de Apuração"),IF(D20="EUR",IF(AND(ISNUMBER(Premissas!B14),Premissas!B14>0),Premissas!B14,"Sem Capacidade de Apuração"),"Sem Capacidade de Apuração"))),"Sem Capacidade de Apuração"),"Sem Capacidade de Apuração")) -> Sem Capacidade de Apuração | H20: =IF(ISNUMBER(F20),"OK","Pendente") -> Pendente
A21: Equipe comercial / parcela fixa | B21: Pendente | F21: =IF(B21="Não se aplica",IF(G21<>"",0,"Sem Capacidade de Apuração"),IF(AND(B21="Informado",COUNT(C21,E21)=2,C21>=0,E21>=0,E21<=1,G21<>""),IF(ISNUMBER(IF(D21="BRL",1,IF(D21="USD",IF(AND(ISNUMBER(Premissas!B13),Premissas!B13>0),Premissas!B13,"Sem Capacidade de Apuração"),IF(D21="EUR",IF(AND(ISNUMBER(Premissas!B14),Premissas!B14>0),Premissas!B14,"Sem Capacidade de Apuração"),"Sem Capacidade de Apuração")))),C21*E21*IF(D21="BRL",1,IF(D21="USD",IF(AND(ISNUMBER(Premissas!B13),Premissas!B13>0),Premissas!B13,"Sem Capacidade de Apuração"),IF(D21="EUR",IF(AND(ISNUMBER(Premissas!B14),Premissas!B14>0),Premissas!B14,"Sem Capacidade de Apuração"),"Sem Capacidade de Apuração"))),"Sem Capacidade de Apuração"),"Sem Capacidade de Apuração")) -> Sem Capacidade de Apuração | H21: =IF(ISNUMBER(F21),"OK","Pendente") -> Pendente
A22: Contabilidade / obrigações fiscais | B22: Pendente | F22: =IF(B22="Não se aplica",IF(G22<>"",0,"Sem Capacidade de Apuração"),IF(AND(B22="Informado",COUNT(C22,E22)=2,C22>=0,E22>=0,E22<=1,G22<>""),IF(ISNUMBER(IF(D22="BRL",1,IF(D22="USD",IF(AND(ISNUMBER(Premissas!B13),Premissas!B13>0),Premissas!B13,"Sem Capacidade de Apuração"),IF(D22="EUR",IF(AND(ISNUMBER(Premissas!B14),Premissas!B14>0),Premissas!B14,"Sem Capacidade de Apuração"),"Sem Capacidade de Apuração")))),C22*E22*IF(D22="BRL",1,IF(D22="USD",IF(AND(ISNUMBER(Premissas!B13),Premissas!B13>0),Premissas!B13,"Sem Capacidade de Apuração"),IF(D22="EUR",IF(AND(ISNUMBER(Premissas!B14),Premissas!B14>0),Premissas!B14,"Sem Capacidade de Apuração"),"Sem Capacidade de Apuração"))),"Sem Capacidade de Apuração"),"Sem Capacidade de Apuração")) -> Sem Capacidade de Apuração | H22: =IF(ISNUMBER(F22),"OK","Pendente") -> Pendente
A23: Jurídico / contratos / LGPD / encarregado | B23: Pendente | F23: =IF(B23="Não se aplica",IF(G23<>"",0,"Sem Capacidade de Apuração"),IF(AND(B23="Informado",COUNT(C23,E23)=2,C23>=0,E23>=0,E23<=1,G23<>""),IF(ISNUMBER(IF(D23="BRL",1,IF(D23="USD",IF(AND(ISNUMBER(Premissas!B13),Premissas!B13>0),Premissas!B13,"Sem Capacidade de Apuração"),IF(D23="EUR",IF(AND(ISNUMBER(Premissas!B14),Premissas!B14>0),Premissas!B14,"Sem Capacidade de Apuração"),"Sem Capacidade de Apuração")))),C23*E23*IF(D23="BRL",1,IF(D23="USD",IF(AND(ISNUMBER(Premissas!B13),Premissas!B13>0),Premissas!B13,"Sem Capacidade de Apuração"),IF(D23="EUR",IF(AND(ISNUMBER(Premissas!B14),Premissas!B14>0),Premissas!B14,"Sem Capacidade de Apuração"),"Sem Capacidade de Apuração"))),"Sem Capacidade de Apuração"),"Sem Capacidade de Apuração")) -> Sem Capacidade de Apuração | H23: =IF(ISNUMBER(F23),"OK","Pendente") -> Pendente
A24: Seguros / responsabilidade / cibernético | B24: Pendente | F24: =IF(B24="Não se aplica",IF(G24<>"",0,"Sem Capacidade de Apuração"),IF(AND(B24="Informado",COUNT(C24,E24)=2,C24>=0,E24>=0,E24<=1,G24<>""),IF(ISNUMBER(IF(D24="BRL",1,IF(D24="USD",IF(AND(ISNUMBER(Premissas!B13),Premissas!B13>0),Premissas!B13,"Sem Capacidade de Apuração"),IF(D24="EUR",IF(AND(ISNUMBER(Premissas!B14),Premissas!B14>0),Premissas!B14,"Sem Capacidade de Apuração"),"Sem Capacidade de Apuração")))),C24*E24*IF(D24="BRL",1,IF(D24="USD",IF(AND(ISNUMBER(Premissas!B13),Premissas!B13>0),Premissas!B13,"Sem Capacidade de Apuração"),IF(D24="EUR",IF(AND(ISNUMBER(Premissas!B14),Premissas!B14>0),Premissas!B14,"Sem Capacidade de Apuração"),"Sem Capacidade de Apuração"))),"Sem Capacidade de Apuração"),"Sem Capacidade de Apuração")) -> Sem Capacidade de Apuração | H24: =IF(ISNUMBER(F24),"OK","Pendente") -> Pendente
A25: Marketing / mídia / aquisição | B25: Pendente | F25: =IF(B25="Não se aplica",IF(G25<>"",0,"Sem Capacidade de Apuração"),IF(AND(B25="Informado",COUNT(C25,E25)=2,C25>=0,E25>=0,E25<=1,G25<>""),IF(ISNUMBER(IF(D25="BRL",1,IF(D25="USD",IF(AND(ISNUMBER(Premissas!B13),Premissas!B13>0),Premissas!B13,"Sem Capacidade de Apuração"),IF(D25="EUR",IF(AND(ISNUMBER(Premissas!B14),Premissas!B14>0),Premissas!B14,"Sem Capacidade de Apuração"),"Sem Capacidade de Apuração")))),C25*E25*IF(D25="BRL",1,IF(D25="USD",IF(AND(ISNUMBER(Premissas!B13),Premissas!B13>0),Premissas!B13,"Sem Capacidade de Apuração"),IF(D25="EUR",IF(AND(ISNUMBER(Premissas!B14),Premissas!B14>0),Premissas!B14,"Sem Capacidade de Apuração"),"Sem Capacidade de Apuração"))),"Sem Capacidade de Apuração"),"Sem Capacidade de Apuração")) -> Sem Capacidade de Apuração | H25: =IF(ISNUMBER(F25),"OK","Pendente") -> Pendente
A26: Ferramentas de trabalho e licenças | B26: Pendente | F26: =IF(B26="Não se aplica",IF(G26<>"",0,"Sem Capacidade de Apuração"),IF(AND(B26="Informado",COUNT(C26,E26)=2,C26>=0,E26>=0,E26<=1,G26<>""),IF(ISNUMBER(IF(D26="BRL",1,IF(D26="USD",IF(AND(ISNUMBER(Premissas!B13),Premissas!B13>0),Premissas!B13,"Sem Capacidade de Apuração"),IF(D26="EUR",IF(AND(ISNUMBER(Premissas!B14),Premissas!B14>0),Premissas!B14,"Sem Capacidade de Apuração"),"Sem Capacidade de Apuração")))),C26*E26*IF(D26="BRL",1,IF(D26="USD",IF(AND(ISNUMBER(Premissas!B13),Premissas!B13>0),Premissas!B13,"Sem Capacidade de Apuração"),IF(D26="EUR",IF(AND(ISNUMBER(Premissas!B14),Premissas!B14>0),Premissas!B14,"Sem Capacidade de Apuração"),"Sem Capacidade de Apuração"))),"Sem Capacidade de Apuração"),"Sem Capacidade de Apuração")) -> Sem Capacidade de Apuração | H26: =IF(ISNUMBER(F26),"OK","Pendente") -> Pendente
A27: Aluguel / internet / energia rateados | B27: Pendente | F27: =IF(B27="Não se aplica",IF(G27<>"",0,"Sem Capacidade de Apuração"),IF(AND(B27="Informado",COUNT(C27,E27)=2,C27>=0,E27>=0,E27<=1,G27<>""),IF(ISNUMBER(IF(D27="BRL",1,IF(D27="USD",IF(AND(ISNUMBER(Premissas!B13),Premissas!B13>0),Premissas!B13,"Sem Capacidade de Apuração"),IF(D27="EUR",IF(AND(ISNUMBER(Premissas!B14),Premissas!B14>0),Premissas!B14,"Sem Capacidade de Apuração"),"Sem Capacidade de Apuração")))),C27*E27*IF(D27="BRL",1,IF(D27="USD",IF(AND(ISNUMBER(Premissas!B13),Premissas!B13>0),Premissas!B13,"Sem Capacidade de Apuração"),IF(D27="EUR",IF(AND(ISNUMBER(Premissas!B14),Premissas!B14>0),Premissas!B14,"Sem Capacidade de Apuração"),"Sem Capacidade de Apuração"))),"Sem Capacidade de Apuração"),"Sem Capacidade de Apuração")) -> Sem Capacidade de Apuração | H27: =IF(ISNUMBER(F27),"OK","Pendente") -> Pendente
A28: Tarifas bancárias fixas | B28: Pendente | F28: =IF(B28="Não se aplica",IF(G28<>"",0,"Sem Capacidade de Apuração"),IF(AND(B28="Informado",COUNT(C28,E28)=2,C28>=0,E28>=0,E28<=1,G28<>""),IF(ISNUMBER(IF(D28="BRL",1,IF(D28="USD",IF(AND(ISNUMBER(Premissas!B13),Premissas!B13>0),Premissas!B13,"Sem Capacidade de Apuração"),IF(D28="EUR",IF(AND(ISNUMBER(Premissas!B14),Premissas!B14>0),Premissas!B14,"Sem Capacidade de Apuração"),"Sem Capacidade de Apuração")))),C28*E28*IF(D28="BRL",1,IF(D28="USD",IF(AND(ISNUMBER(Premissas!B13),Premissas!B13>0),Premissas!B13,"Sem Capacidade de Apuração"),IF(D28="EUR",IF(AND(ISNUMBER(Premissas!B14),Premissas!B14>0),Premissas!B14,"Sem Capacidade de Apuração"),"Sem Capacidade de Apuração"))),"Sem Capacidade de Apuração"),"Sem Capacidade de Apuração")) -> Sem Capacidade de Apuração | H28: =IF(ISNUMBER(F28),"OK","Pendente") -> Pendente
A29: Depreciação / amortização de equipamentos | B29: Pendente | F29: =IF(B29="Não se aplica",IF(G29<>"",0,"Sem Capacidade de Apuração"),IF(AND(B29="Informado",COUNT(C29,E29)=2,C29>=0,E29>=0,E29<=1,G29<>""),IF(ISNUMBER(IF(D29="BRL",1,IF(D29="USD",IF(AND(ISNUMBER(Premissas!B13),Premissas!B13>0),Premissas!B13,"Sem Capacidade de Apuração"),IF(D29="EUR",IF(AND(ISNUMBER(Premissas!B14),Premissas!B14>0),Premissas!B14,"Sem Capacidade de Apuração"),"Sem Capacidade de Apuração")))),C29*E29*IF(D29="BRL",1,IF(D29="USD",IF(AND(ISNUMBER(Premissas!B13),Premissas!B13>0),Premissas!B13,"Sem Capacidade de Apuração"),IF(D29="EUR",IF(AND(ISNUMBER(Premissas!B14),Premissas!B14>0),Premissas!B14,"Sem Capacidade de Apuração"),"Sem Capacidade de Apuração"))),"Sem Capacidade de Apuração"),"Sem Capacidade de Apuração")) -> Sem Capacidade de Apuração | H29: =IF(ISNUMBER(F29),"OK","Pendente") -> Pendente
A30: Amortização do desenvolvimento inicial | B30: Pendente | F30: =IF(B30="Não se aplica",IF(G30<>"",0,"Sem Capacidade de Apuração"),IF(AND(B30="Informado",COUNT(C30,E30)=2,C30>=0,E30>=0,E30<=1,G30<>""),IF(ISNUMBER(IF(D30="BRL",1,IF(D30="USD",IF(AND(ISNUMBER(Premissas!B13),Premissas!B13>0),Premissas!B13,"Sem Capacidade de Apuração"),IF(D30="EUR",IF(AND(ISNUMBER(Premissas!B14),Premissas!B14>0),Premissas!B14,"Sem Capacidade de Apuração"),"Sem Capacidade de Apuração")))),C30*E30*IF(D30="BRL",1,IF(D30="USD",IF(AND(ISNUMBER(Premissas!B13),Premissas!B13>0),Premissas!B13,"Sem Capacidade de Apuração"),IF(D30="EUR",IF(AND(ISNUMBER(Premissas!B14),Premissas!B14>0),Premissas!B14,"Sem Capacidade de Apuração"),"Sem Capacidade de Apuração"))),"Sem Capacidade de Apuração"),"Sem Capacidade de Apuração")) -> Sem Capacidade de Apuração | H30: =IF(ISNUMBER(F30),"OK","Pendente") -> Pendente
A31: Treinamento / implantação de clientes | B31: Pendente | F31: =IF(B31="Não se aplica",IF(G31<>"",0,"Sem Capacidade de Apuração"),IF(AND(B31="Informado",COUNT(C31,E31)=2,C31>=0,E31>=0,E31<=1,G31<>""),IF(ISNUMBER(IF(D31="BRL",1,IF(D31="USD",IF(AND(ISNUMBER(Premissas!B13),Premissas!B13>0),Premissas!B13,"Sem Capacidade de Apuração"),IF(D31="EUR",IF(AND(ISNUMBER(Premissas!B14),Premissas!B14>0),Premissas!B14,"Sem Capacidade de Apuração"),"Sem Capacidade de Apuração")))),C31*E31*IF(D31="BRL",1,IF(D31="USD",IF(AND(ISNUMBER(Premissas!B13),Premissas!B13>0),Premissas!B13,"Sem Capacidade de Apuração"),IF(D31="EUR",IF(AND(ISNUMBER(Premissas!B14),Premissas!B14>0),Premissas!B14,"Sem Capacidade de Apuração"),"Sem Capacidade de Apuração"))),"Sem Capacidade de Apuração"),"Sem Capacidade de Apuração")) -> Sem Capacidade de Apuração | H31: =IF(ISNUMBER(F31),"OK","Pendente") -> Pendente
A32: Contestações Stripe — tarifas líquidas | B32: Pendente | F32: =IF(B32="Não se aplica",IF(G32<>"",0,"Sem Capacidade de Apuração"),IF(AND(B32="Informado",COUNT(C32,E32)=2,C32>=0,E32>=0,E32<=1,G32<>""),IF(ISNUMBER(IF(D32="BRL",1,IF(D32="USD",IF(AND(ISNUMBER(Premissas!B13),Premissas!B13>0),Premissas!B13,"Sem Capacidade de Apuração"),IF(D32="EUR",IF(AND(ISNUMBER(Premissas!B14),Premissas!B14>0),Premissas!B14,"Sem Capacidade de Apuração"),"Sem Capacidade de Apuração")))),C32*E32*IF(D32="BRL",1,IF(D32="USD",IF(AND(ISNUMBER(Premissas!B13),Premissas!B13>0),Premissas!B13,"Sem Capacidade de Apuração"),IF(D32="EUR",IF(AND(ISNUMBER(Premissas!B14),Premissas!B14>0),Premissas!B14,"Sem Capacidade de Apuração"),"Sem Capacidade de Apuração"))),"Sem Capacidade de Apuração"),"Sem Capacidade de Apuração")) -> Sem Capacidade de Apuração | H32: =IF(ISNUMBER(F32),"OK","Pendente") -> Pendente
A33: Outros custos fixos ou periódicos | B33: Pendente | F33: =IF(B33="Não se aplica",IF(G33<>"",0,"Sem Capacidade de Apuração"),IF(AND(B33="Informado",COUNT(C33,E33)=2,C33>=0,E33>=0,E33<=1,G33<>""),IF(ISNUMBER(IF(D33="BRL",1,IF(D33="USD",IF(AND(ISNUMBER(Premissas!B13),Premissas!B13>0),Premissas!B13,"Sem Capacidade de Apuração"),IF(D33="EUR",IF(AND(ISNUMBER(Premissas!B14),Premissas!B14>0),Premissas!B14,"Sem Capacidade de Apuração"),"Sem Capacidade de Apuração")))),C33*E33*IF(D33="BRL",1,IF(D33="USD",IF(AND(ISNUMBER(Premissas!B13),Premissas!B13>0),Premissas!B13,"Sem Capacidade de Apuração"),IF(D33="EUR",IF(AND(ISNUMBER(Premissas!B14),Premissas!B14>0),Premissas!B14,"Sem Capacidade de Apuração"),"Sem Capacidade de Apuração"))),"Sem Capacidade de Apuração"),"Sem Capacidade de Apuração")) -> Sem Capacidade de Apuração | H33: =IF(ISNUMBER(F33),"OK","Pendente") -> Pendente
A35: TOTAL MENSAL PSIQUE | F35: =IF(COUNT(F6:F33)=28,SUM(F6:F33),"Sem Capacidade de Apuração") -> Sem Capacidade de Apuração
A37: PENDÊNCIAS | F37: =28-COUNT(F6:F33) -> 28

Sheet Variaveis
A1: OUTROS CUSTOS | Por atendimento
A2: Somente incrementais fora de IA e Fixos. Faturas do acervo total ficam em Fixos. Não duplicar parcelas já incluídas na mensalidade.
A5: Item | B5: Tratamento | C5: Qtd/atendimento | D5: BRL/unidade | E5: BRL/atendimento | F5: Fonte / justificativa
A6: Tráfego excedente / relay TURN (GB) | B6: Pendente | E6: =IF(B6="Não se aplica",IF(F6<>"",0,"Sem Capacidade de Apuração"),IF(AND(B6="Informado",COUNT(C6,D6)=2,C6>=0,D6>=0,F6<>""),C6*D6,"Sem Capacidade de Apuração")) -> Sem Capacidade de Apuração
A7: Armazenamento incremental não faturado em Fixos | B7: Pendente | E7: =IF(B7="Não se aplica",IF(F7<>"",0,"Sem Capacidade de Apuração"),IF(AND(B7="Informado",COUNT(C7,D7)=2,C7>=0,D7>=0,F7<>""),C7*D7,"Sem Capacidade de Apuração")) -> Sem Capacidade de Apuração
A8: Mensagens / e-mails / notificações | B8: Pendente | E8: =IF(B8="Não se aplica",IF(F8<>"",0,"Sem Capacidade de Apuração"),IF(AND(B8="Informado",COUNT(C8,D8)=2,C8>=0,D8>=0,F8<>""),C8*D8,"Sem Capacidade de Apuração")) -> Sem Capacidade de Apuração
A9: Suporte variável (minutos) | B9: Pendente | E9: =IF(B9="Não se aplica",IF(F9<>"",0,"Sem Capacidade de Apuração"),IF(AND(B9="Informado",COUNT(C9,D9)=2,C9>=0,D9>=0,F9<>""),C9*D9,"Sem Capacidade de Apuração")) -> Sem Capacidade de Apuração
A10: Implantação/treinamento amortizado por crédito | B10: Pendente | E10: =IF(B10="Não se aplica",IF(F10<>"",0,"Sem Capacidade de Apuração"),IF(AND(B10="Informado",COUNT(C10,D10)=2,C10>=0,D10>=0,F10<>""),C10*D10,"Sem Capacidade de Apuração")) -> Sem Capacidade de Apuração
A11: Serviços terceirizados por atendimento | B11: Pendente | E11: =IF(B11="Não se aplica",IF(F11<>"",0,"Sem Capacidade de Apuração"),IF(AND(B11="Informado",COUNT(C11,D11)=2,C11>=0,D11>=0,F11<>""),C11*D11,"Sem Capacidade de Apuração")) -> Sem Capacidade de Apuração
A12: Emissão de nota / documento (parcela variável) | B12: Pendente | E12: =IF(B12="Não se aplica",IF(F12<>"",0,"Sem Capacidade de Apuração"),IF(AND(B12="Informado",COUNT(C12,D12)=2,C12>=0,D12>=0,F12<>""),C12*D12,"Sem Capacidade de Apuração")) -> Sem Capacidade de Apuração
A13: Outras APIs em BRL não lançadas em IA | B13: Pendente | E13: =IF(B13="Não se aplica",IF(F13<>"",0,"Sem Capacidade de Apuração"),IF(AND(B13="Informado",COUNT(C13,D13)=2,C13>=0,D13>=0,F13<>""),C13*D13,"Sem Capacidade de Apuração")) -> Sem Capacidade de Apuração
A14: Outros custos incrementais | B14: Pendente | E14: =IF(B14="Não se aplica",IF(F14<>"",0,"Sem Capacidade de Apuração"),IF(AND(B14="Informado",COUNT(C14,D14)=2,C14>=0,D14>=0,F14<>""),C14*D14,"Sem Capacidade de Apuração")) -> Sem Capacidade de Apuração
A16: TOTAL POR ATENDIMENTO | E16: =IF(COUNT(E6:E14)=9,SUM(E6:E14),"Sem Capacidade de Apuração") -> Sem Capacidade de Apuração
A18: PENDÊNCIAS | E18: =9-COUNT(E6:E14) -> 9

Sheet Resultado
A1: RESULTADO | Custo, margem e equilíbrio
A2: Custo completo só aparece quando todas as dependências forem preenchidas. Projeções não são faturas. As premissas definem a precisão.
A5: Indicador | B5: Valor | C5: Interpretação
A6: Custo fixo mensal | B6: =Fixos!F35 -> Sem Capacidade de Apuração | C6: Parcela atribuída ao Psique.
A7: IA por atendimento | B7: =IA!G16 -> Sem Capacidade de Apuração | C7: Tarifa pública × consumo informado × câmbio efetivo.
A8: Outros variáveis por atendimento | B8: =Variaveis!E16 -> Sem Capacidade de Apuração | C8: Incrementais fora de IA.
A9: Variável total por atendimento | B9: =IF(COUNT(B7:B8)=2,SUM(B7:B8),"Sem Capacidade de Apuração") -> Sem Capacidade de Apuração | C9: Pago ou gratuito.
A10: Custos operacionais totais no mês | B10: =IF(AND(COUNT(B6,B9,Premissas!B8)=3,Premissas!B8>=0),B6+B9*Premissas!B8,"Sem Capacidade de Apuração") -> Sem Capacidade de Apuração | C10: Fixo + variável × atendimentos pagos e gratuitos.
A11: Custo operacional por crédito pago | B11: =IF(AND(COUNT(B10,Premissas!B6)=2,Premissas!B6>0),B10/Premissas!B6,"Sem Capacidade de Apuração") -> Sem Capacidade de Apuração | C11: Inclui gratuitos e estrutura. Ainda sem tributos/taxas da venda.
A12: Deduções percentuais sobre receita | B12: =IF(COUNT(Premissas!B15:B18,Premissas!B20)=5,SUM(Premissas!B15:B18,Premissas!B20),"Sem Capacidade de Apuração") -> Sem Capacidade de Apuração | C12: Tributos + comissões + perdas + pagamento + adicionais.
A13: Tarifa fixa por crédito pago | B13: =IF(AND(COUNT(Premissas!B19,Premissas!B10)=2,Premissas!B10>0),Premissas!B19/Premissas!B10,"Sem Capacidade de Apuração") -> Sem Capacidade de Apuração | C13: Tarifa por transação dividida pelos créditos do pacote.
A14: Preço de equilíbrio por crédito | B14: =IF(COUNT(B11:B13)=3,IF(B12<1,(B11+B13)/(1-B12),"Inviável"),"Sem Capacidade de Apuração") -> Sem Capacidade de Apuração | C14: Cobre custos informados com margem zero.
A15: Preço mínimo para margem desejada | B15: =IF(COUNT(B11:B13,Premissas!B12)=4,IF(B12+Premissas!B12<1,(B11+B13)/(1-B12-Premissas!B12),"Inviável"),"Sem Capacidade de Apuração") -> Sem Capacidade de Apuração | C15: Custo dividido pela receita restante após taxas e margem-alvo.
A17: Receita mensal ao preço avaliado | B17: =IF(AND(COUNT(Premissas!B6,Premissas!B11)=2,Premissas!B6>0,Premissas!B11>0),Premissas!B6*Premissas!B11,"Sem Capacidade de Apuração") -> Sem Capacidade de Apuração | C17: Receita gerencial dos créditos pagos utilizados; não caixa das compras antecipadas.
A18: Deduções percentuais em BRL | B18: =IF(COUNT(B17,B12)=2,B17*B12,"Sem Capacidade de Apuração") -> Sem Capacidade de Apuração | C18: Não inclui tarifa fixa.
A19: Tarifas fixas de pagamento no mês | B19: =IF(COUNT(B13,Premissas!B6)=2,B13*Premissas!B6,"Sem Capacidade de Apuração") -> Sem Capacidade de Apuração | C19: Rateio pelos créditos comprados.
A20: Custos totais com cobrança e tributos | B20: =IF(COUNT(B10,B18:B19)=3,SUM(B10,B18:B19),"Sem Capacidade de Apuração") -> Sem Capacidade de Apuração | C20: Operação + deduções + tarifas fixas.
A21: Resultado operacional mensal | B21: =IF(COUNT(B17,B20)=2,B17-B20,"Sem Capacidade de Apuração") -> Sem Capacidade de Apuração | C21: Receita menos custos informados.
A22: Margem operacional | B22: =IF(COUNT(B17,B21)=2,IF(B17>0,B21/B17,"Inviável"),"Sem Capacidade de Apuração") -> Sem Capacidade de Apuração | C22: Projeção se as entradas forem hipóteses.
A23: Créditos pagos para atingir equilíbrio | B23: =IF(COUNT(B6,B9,B12,B13,Premissas!B7,Premissas!B11)=6,IF(Premissas!B11*(1-B12)-B9-B13>0,ROUNDUP((B6+B9*Premissas!B7)/(Premissas!B11*(1-B12)-B9-B13),0),"Inviável"),"Sem Capacidade de Apuração") -> Sem Capacidade de Apuração | C23: Mantém estrutura, gratuitos e custo unitário constantes. Mudança de capacidade exige recalcular.
A25: Itens de custo ainda pendentes | B25: =SUM(IA!G18,Fixos!F37,Variaveis!E18) -> 46 | C25: Além destes, premissas comerciais/câmbio também podem faltar.

Sheet Pacotes
A1: PACOTES | Referências e valores em avaliação
A2: Nenhum preço novo é aprovado aqui. MASTER: site e catálogo divergem; não usar valor de teste como decisão comercial.
A5: Plano | B5: Créditos site | C5: Usuários | D5: Total site BRL | E5: Créditos catálogo | F5: Total catálogo BRL | G5: Preço/crédito site | H5: Novo total (entrada) | I5: Novo preço/crédito | J5: Custo operacional | K5: Taxas/tributos | L5: Resultado pacote | M5: Margem | N5: Mínimo p/ margem-alvo
A6: PRO | B6: 10 | C6: 1 | D6: 198 | E6: 10 | F6: 198 | G6: =D6/B6 -> 19.8 | I6: =IF(COUNT(H6)=1,H6/B6,"Sem Capacidade de Apuração") -> Sem Capacidade de Apuração | J6: =IF(ISNUMBER(Resultado!B11),Resultado!B11*B6,"Sem Capacidade de Apuração") -> Sem Capacidade de Apuração | K6: =IF(COUNT(H6,Resultado!B12,Premissas!B19)=3,H6*Resultado!B12+Premissas!B19,"Sem Capacidade de Apuração") -> Sem Capacidade de Apuração | L6: =IF(COUNT(H6,J6,K6)=3,H6-J6-K6,"Sem Capacidade de Apuração") -> Sem Capacidade de Apuração | M6: =IF(COUNT(H6,L6)=2,IF(H6>0,L6/H6,"Inviável"),"Sem Capacidade de Apuração") -> Sem Capacidade de Apuração | N6: =IF(COUNT(J6,Resultado!B12,Premissas!B12,Premissas!B19)=4,IF(Resultado!B12+Premissas!B12<1,(J6+Premissas!B19)/(1-Resultado!B12-Premissas!B12),"Inviável"),"Sem Capacidade de Apuração") -> Sem Capacidade de Apuração
A7: PRO | B7: 25 | C7: 1 | D7: 470 | E7: 25 | F7: 470 | G7: =D7/B7 -> 18.8 | I7: =IF(COUNT(H7)=1,H7/B7,"Sem Capacidade de Apuração") -> Sem Capacidade de Apuração | J7: =IF(ISNUMBER(Resultado!B11),Resultado!B11*B7,"Sem Capacidade de Apuração") -> Sem Capacidade de Apuração | K7: =IF(COUNT(H7,Resultado!B12,Premissas!B19)=3,H7*Resultado!B12+Premissas!B19,"Sem Capacidade de Apuração") -> Sem Capacidade de Apuração | L7: =IF(COUNT(H7,J7,K7)=3,H7-J7-K7,"Sem Capacidade de Apuração") -> Sem Capacidade de Apuração | M7: =IF(COUNT(H7,L7)=2,IF(H7>0,L7/H7,"Inviável"),"Sem Capacidade de Apuração") -> Sem Capacidade de Apuração | N7: =IF(COUNT(J7,Resultado!B12,Premissas!B12,Premissas!B19)=4,IF(Resultado!B12+Premissas!B12<1,(J7+Premissas!B19)/(1-Resultado!B12-Premissas!B12),"Inviável"),"Sem Capacidade de Apuração") -> Sem Capacidade de Apuração
A8: PLUS | B8: 50 | C8: 10 | D8: 1182 | E8: 50 | F8: 1182 | G8: =D8/B8 -> 23.64 | I8: =IF(COUNT(H8)=1,H8/B8,"Sem Capacidade de Apuração") -> Sem Capacidade de Apuração | J8: =IF(ISNUMBER(Resultado!B11),Resultado!B11*B8,"Sem Capacidade de Apuração") -> Sem Capacidade de Apuração | K8: =IF(COUNT(H8,Resultado!B12,Premissas!B19)=3,H8*Resultado!B12+Premissas!B19,"Sem Capacidade de Apuração") -> Sem Capacidade de Apuração | L8: =IF(COUNT(H8,J8,K8)=3,H8-J8-K8,"Sem Capacidade de Apuração") -> Sem Capacidade de Apuração | M8: =IF(COUNT(H8,L8)=2,IF(H8>0,L8/H8,"Inviável"),"Sem Capacidade de Apuração") -> Sem Capacidade de Apuração | N8: =IF(COUNT(J8,Resultado!B12,Premissas!B12,Premissas!B19)=4,IF(Resultado!B12+Premissas!B12<1,(J8+Premissas!B19)/(1-Resultado!B12-Premissas!B12),"Inviável"),"Sem Capacidade de Apuração") -> Sem Capacidade de Apuração
A9: PLUS | B9: 100 | C9: 10 | D9: 2202 | E9: 100 | F9: 2202 | G9: =D9/B9 -> 22.02 | I9: =IF(COUNT(H9)=1,H9/B9,"Sem Capacidade de Apuração") -> Sem Capacidade de Apuração | J9: =IF(ISNUMBER(Resultado!B11),Resultado!B11*B9,"Sem Capacidade de Apuração") -> Sem Capacidade de Apuração | K9: =IF(COUNT(H9,Resultado!B12,Premissas!B19)=3,H9*Resultado!B12+Premissas!B19,"Sem Capacidade de Apuração") -> Sem Capacidade de Apuração | L9: =IF(COUNT(H9,J9,K9)=3,H9-J9-K9,"Sem Capacidade de Apuração") -> Sem Capacidade de Apuração | M9: =IF(COUNT(H9,L9)=2,IF(H9>0,L9/H9,"Inviável"),"Sem Capacidade de Apuração") -> Sem Capacidade de Apuração | N9: =IF(COUNT(J9,Resultado!B12,Premissas!B12,Premissas!B19)=4,IF(Resultado!B12+Premissas!B12<1,(J9+Premissas!B19)/(1-Resultado!B12-Premissas!B12),"Inviável"),"Sem Capacidade de Apuração") -> Sem Capacidade de Apuração
A10: MASTER | B10: 200 | C10: 35 | D10: 4888 | E10: 25 | F10: 20 | G10: =D10/B10 -> 24.44 | I10: =IF(COUNT(H10)=1,H10/B10,"Sem Capacidade de Apuração") -> Sem Capacidade de Apuração | J10: =IF(ISNUMBER(Resultado!B11),Resultado!B11*B10,"Sem Capacidade de Apuração") -> Sem Capacidade de Apuração | K10: =IF(COUNT(H10,Resultado!B12,Premissas!B19)=3,H10*Resultado!B12+Premissas!B19,"Sem Capacidade de Apuração") -> Sem Capacidade de Apuração | L10: =IF(COUNT(H10,J10,K10)=3,H10-J10-K10,"Sem Capacidade de Apuração") -> Sem Capacidade de Apuração | M10: =IF(COUNT(H10,L10)=2,IF(H10>0,L10/H10,"Inviável"),"Sem Capacidade de Apuração") -> Sem Capacidade de Apuração | N10: =IF(COUNT(J10,Resultado!B12,Premissas!B12,Premissas!B19)=4,IF(Resultado!B12+Premissas!B12<1,(J10+Premissas!B19)/(1-Resultado!B12-Premissas!B12),"Inviável"),"Sem Capacidade de Apuração") -> Sem Capacidade de Apuração
A12: MASTER: site = 200 créditos / R$ 4.888; catálogo consultado = 25 / R$ 20. Divergência registrada, sem adoção como novo preço.
A14: Preço por crédito = total do pacote / quantidade. Não utiliza o campo unitário de referência comercial, que pode divergir dessa divisão.
A16: Fontes: froid-server/subscriptions.py e https://www.froid.com.br/precos.html. Preços de referência, sujeitos à decisão do proprietário.

Sheet Cenarios
A1: CENÁRIOS | Volume e preço escolhidos por você
A2: Nenhum volume ou preço foi presumido. Mesmos fixos, variável unitário e taxas do cenário base. Capacidade extra deve ser orçada.
A5: Cenário | B5: Pagos/mês | C5: Gratuitos/mês | D5: BRL/crédito | E5: Receita mensal | F5: Custo completo | G5: Resultado mensal | H5: Margem | I5: Preço equilíbrio
A6: Cenário 1 | E6: =IF(AND(COUNT(B6,D6)=2,B6>0,D6>0),B6*D6,"Sem Capacidade de Apuração") -> Sem Capacidade de Apuração | F6: =IF(AND(COUNT(B6:D6,E6,Resultado!B6,Resultado!B9,Resultado!B12,Resultado!B13)=8,B6>0,C6>=0),Resultado!B6+Resultado!B9*(B6+C6)+E6*Resultado!B12+Resultado!B13*B6,"Sem Capacidade de Apuração") -> Sem Capacidade de Apuração | G6: =IF(COUNT(E6:F6)=2,E6-F6,"Sem Capacidade de Apuração") -> Sem Capacidade de Apuração | H6: =IF(COUNT(E6,G6)=2,IF(E6>0,G6/E6,"Inviável"),"Sem Capacidade de Apuração") -> Sem Capacidade de Apuração | I6: =IF(AND(COUNT(B6:C6,Resultado!B6,Resultado!B9,Resultado!B12,Resultado!B13)=6,B6>0,C6>=0),IF(Resultado!B12<1,(Resultado!B6/B6+Resultado!B9*(1+C6/B6)+Resultado!B13)/(1-Resultado!B12),"Inviável"),"Sem Capacidade de Apuração") -> Sem Capacidade de Apuração
A7: Cenário 2 | E7: =IF(AND(COUNT(B7,D7)=2,B7>0,D7>0),B7*D7,"Sem Capacidade de Apuração") -> Sem Capacidade de Apuração | F7: =IF(AND(COUNT(B7:D7,E7,Resultado!B6,Resultado!B9,Resultado!B12,Resultado!B13)=8,B7>0,C7>=0),Resultado!B6+Resultado!B9*(B7+C7)+E7*Resultado!B12+Resultado!B13*B7,"Sem Capacidade de Apuração") -> Sem Capacidade de Apuração | G7: =IF(COUNT(E7:F7)=2,E7-F7,"Sem Capacidade de Apuração") -> Sem Capacidade de Apuração | H7: =IF(COUNT(E7,G7)=2,IF(E7>0,G7/E7,"Inviável"),"Sem Capacidade de Apuração") -> Sem Capacidade de Apuração | I7: =IF(AND(COUNT(B7:C7,Resultado!B6,Resultado!B9,Resultado!B12,Resultado!B13)=6,B7>0,C7>=0),IF(Resultado!B12<1,(Resultado!B6/B7+Resultado!B9*(1+C7/B7)+Resultado!B13)/(1-Resultado!B12),"Inviável"),"Sem Capacidade de Apuração") -> Sem Capacidade de Apuração
A8: Cenário 3 | E8: =IF(AND(COUNT(B8,D8)=2,B8>0,D8>0),B8*D8,"Sem Capacidade de Apuração") -> Sem Capacidade de Apuração | F8: =IF(AND(COUNT(B8:D8,E8,Resultado!B6,Resultado!B9,Resultado!B12,Resultado!B13)=8,B8>0,C8>=0),Resultado!B6+Resultado!B9*(B8+C8)+E8*Resultado!B12+Resultado!B13*B8,"Sem Capacidade de Apuração") -> Sem Capacidade de Apuração | G8: =IF(COUNT(E8:F8)=2,E8-F8,"Sem Capacidade de Apuração") -> Sem Capacidade de Apuração | H8: =IF(COUNT(E8,G8)=2,IF(E8>0,G8/E8,"Inviável"),"Sem Capacidade de Apuração") -> Sem Capacidade de Apuração | I8: =IF(AND(COUNT(B8:C8,Resultado!B6,Resultado!B9,Resultado!B12,Resultado!B13)=6,B8>0,C8>=0),IF(Resultado!B12<1,(Resultado!B6/B8+Resultado!B9*(1+C8/B8)+Resultado!B13)/(1-Resultado!B12),"Inviável"),"Sem Capacidade de Apuração") -> Sem Capacidade de Apuração
A9: Cenário 4 | E9: =IF(AND(COUNT(B9,D9)=2,B9>0,D9>0),B9*D9,"Sem Capacidade de Apuração") -> Sem Capacidade de Apuração | F9: =IF(AND(COUNT(B9:D9,E9,Resultado!B6,Resultado!B9,Resultado!B12,Resultado!B13)=8,B9>0,C9>=0),Resultado!B6+Resultado!B9*(B9+C9)+E9*Resultado!B12+Resultado!B13*B9,"Sem Capacidade de Apuração") -> Sem Capacidade de Apuração | G9: =IF(COUNT(E9:F9)=2,E9-F9,"Sem Capacidade de Apuração") -> Sem Capacidade de Apuração | H9: =IF(COUNT(E9,G9)=2,IF(E9>0,G9/E9,"Inviável"),"Sem Capacidade de Apuração") -> Sem Capacidade de Apuração | I9: =IF(AND(COUNT(B9:C9,Resultado!B6,Resultado!B9,Resultado!B12,Resultado!B13)=6,B9>0,C9>=0),IF(Resultado!B12<1,(Resultado!B6/B9+Resultado!B9*(1+C9/B9)+Resultado!B13)/(1-Resultado!B12),"Inviável"),"Sem Capacidade de Apuração") -> Sem Capacidade de Apuração
A10: Cenário 5 | E10: =IF(AND(COUNT(B10,D10)=2,B10>0,D10>0),B10*D10,"Sem Capacidade de Apuração") -> Sem Capacidade de Apuração | F10: =IF(AND(COUNT(B10:D10,E10,Resultado!B6,Resultado!B9,Resultado!B12,Resultado!B13)=8,B10>0,C10>=0),Resultado!B6+Resultado!B9*(B10+C10)+E10*Resultado!B12+Resultado!B13*B10,"Sem Capacidade de Apuração") -> Sem Capacidade de Apuração | G10: =IF(COUNT(E10:F10)=2,E10-F10,"Sem Capacidade de Apuração") -> Sem Capacidade de Apuração | H10: =IF(COUNT(E10,G10)=2,IF(E10>0,G10/E10,"Inviável"),"Sem Capacidade de Apuração") -> Sem Capacidade de Apuração | I10: =IF(AND(COUNT(B10:C10,Resultado!B6,Resultado!B9,Resultado!B12,Resultado!B13)=6,B10>0,C10>=0),IF(Resultado!B12<1,(Resultado!B6/B10+Resultado!B9*(1+C10/B10)+Resultado!B13)/(1-Resultado!B12),"Inviável"),"Sem Capacidade de Apuração") -> Sem Capacidade de Apuração
