Workbook

Sheet 1. Premissas
A1: FROID Psicossocial — premissas do modelo
A2: Amarelo é entrada: mude à vontade. Azul é fórmula, não edite.
A4: PREÇO DE TABELA
A5: Base da plataforma, por estabelecimento/mês | B5: 1200
A6: Faixa 1 — de 1 a 100 trabalhadores (por trab./mês) | B6: 9
A7: Faixa 2 — de 101 a 300 | B7: 7
A8: Faixa 3 — de 301 a 1.000 | B8: 5
A9: Faixa 4 — acima de 1.000 | B9: 3
A10: Limite da faixa 1 (trabalhadores) | B10: 100
A11: Limite da faixa 2 | B11: 300
A12: Limite da faixa 3 | B12: 1000
A14: DESCONTOS
A15: Pioneiro (até 31/12/2026) | B15: 0.15
A16: Anual: meses pagos em 12 | B16: 10 | C16: 12 meses pagos como 10 = 16,7% de desconto
A17: Canal — faixa média praticada | B17: 0.3 | C17: 20% até 9 clientes · 30% de 10 a 29 · 40% acima de 30
A19: CUSTO FIXO MENSAL
A20: Infraestrutura (servidor, backup, domínio) | B20: 400 | C20: ESTIMATIVA — confirmar com a fatura do Hetzner
A21: Ferramentas e licenças | B21: 300 | C21: ESTIMATIVA — e-mail, repositório, monitoramento
A22: Contabilidade e jurídico | B22: 1500 | C22: ESTIMATIVA — confirmar
A23: Pró-labore e equipe | B23: 0 | C23: PREENCHER — deixei zero de propósito; é o maior custo de quase todo SaaS
A24: Outros fixos | B24: 0
A25: Total de custo fixo mensal | B25: =SUM(B20:B24)
A27: CUSTO VARIÁVEL
A28: Por cliente ativo/mês (suporte, armazenamento) | B28: 40 | C28: ESTIMATIVA
A29: Por trabalhador/mês (consulta ao acervo, e-mail) | B29: 0.25 | C29: ESTIMATIVA — o Explica consome API por consulta
A31: IMPOSTOS
A32: Alíquota efetiva sobre a receita | B32: 0.16 | C32: ESTIMATIVA — Simples Nacional anexo III começa em 6% e sobe com o faturamento. CONFIRMAR com a contabilidade
A34: COMERCIAL
A35: Novos clientes por mês | B35: 2
A36: Cancelamento mensal (churn) | B36: 0.02 | C36: 2% ao mês ≈ 22% ao ano
A37: Clientes já ativos hoje | B37: 0
A38: Trabalhadores por cliente (média) | B38: 250
A39: Estabelecimentos por cliente (média) | B39: 3
A40: Fração vinda por canal (com desconto) | B40: 0.5
A42: O QUE SÓ VOCÊ SABE — as células marcadas ESTIMATIVA acima
A43: 1. A fatura real do servidor e das ferramentas.
A44: 2. O pró-labore que você precisa retirar. Está zerado, e por isso o resultado abaixo é otimista.
A45: 3. O regime tributário. Simples Nacional anexo III começa em 6% e sobe por faixa de faturamento;
A46: Lucro Presumido para serviço fica perto de 13,33% de PIS/COFINS/ISS mais IRPJ e CSLL.
A47: 4. O custo de aquisição: se houver comissão, tráfego pago ou vendedor, entra em fixo ou variável.

Sheet 2. Simulador de cliente
A1: Quanto custa e quanto sobra em UM cliente
A2: Mude trabalhadores e estabelecimentos e veja o efeito na margem.
A4: O CLIENTE
A5: Trabalhadores | B5: 263
A6: Estabelecimentos | B6: 11
A7: Desconto aplicado | B7: 0 | C7: 0 = tabela cheia · 0,15 = pioneiro · 0,30 = canal
A9: RECEITA
A10: Base da plataforma | B10: =B6*'1. Premissas'!B5 | C10: É aqui que mora o peso: base × número de endereços
A11: Escala por trabalhador | B11: =MIN(B5,'1. Premissas'!B10)*'1. Premissas'!B6+MAX(0,MIN(B5,'1. Premissas'!B11)-'1. Premissas'!B10)*'1. Premissas'!B7+MAX(0,MIN(B5,'1. Premissas'!B12)-'1. Premissas'!B11)*'1. Premissas'!B8+MAX(0,B5-'1. Premissas'!B12)*'1. Premissas'!B9 | C11: Faixas cumulativas
A12: Mensal de tabela | B12: =B10+B11
A13: Mensal com desconto | B13: =B12*(1-B7)
A14: Anual | B14: =B13*12
A15: Peso da base no total | B15: =B10/B12 | C15: Acima de 70% significa que você cobra por endereço, não por trabalhador
A17: CUSTO DE SERVIR
A18: Variável por cliente | B18: ='1. Premissas'!B28
A19: Variável por trabalhador | B19: =B5*'1. Premissas'!B29
A20: Impostos | B20: =B13*'1. Premissas'!B32
A21: Custo variável total | B21: =B18+B19+B20
A23: RESULTADO
A24: Margem de contribuição (R$/mês) | B24: =B13-B21
A25: Margem de contribuição (%) | B25: =B24/B13
A26: Receita por trabalhador/mês | B26: =B13/B5 | C26: Número que o cliente calcula sozinho e usa para comparar
A27: Receita por trabalhador/ano | B27: =B13*12/B5
A30: SENSIBILIDADE — o mesmo cliente com bases diferentes
A31: Base por estabelecimento | B31: Mensal | C31: Anual | D31: Por trab./mês | E31: Margem R$ | F31: Margem %
A32: 1200 | B32: =(1200*B6+B11)*(1-B7) | C32: =B32*12 | D32: =B32/B5 | E32: =B32-(B18+B19+B32*'1. Premissas'!B32) | F32: =E32/B32
A33: 1000 | B33: =(1000*B6+B11)*(1-B7) | C33: =B33*12 | D33: =B33/B5 | E33: =B33-(B18+B19+B33*'1. Premissas'!B32) | F33: =E33/B33
A34: 900 | B34: =(900*B6+B11)*(1-B7) | C34: =B34*12 | D34: =B34/B5 | E34: =B34-(B18+B19+B34*'1. Premissas'!B32) | F34: =E34/B34
A35: 800 | B35: =(800*B6+B11)*(1-B7) | C35: =B35*12 | D35: =B35/B5 | E35: =B35-(B18+B19+B35*'1. Premissas'!B32) | F35: =E35/B35
A36: 700 | B36: =(700*B6+B11)*(1-B7) | C36: =B36*12 | D36: =B36/B5 | E36: =B36-(B18+B19+B36*'1. Premissas'!B32) | F36: =E36/B36
A37: 600 | B37: =(600*B6+B11)*(1-B7) | C37: =B37*12 | D37: =B37/B5 | E37: =B37-(B18+B19+B37*'1. Premissas'!B32) | F37: =E37/B37
A38: 500 | B38: =(500*B6+B11)*(1-B7) | C38: =B38*12 | D38: =B38/B5 | E38: =B38-(B18+B19+B38*'1. Premissas'!B32) | F38: =E38/B38
A39: 400 | B39: =(400*B6+B11)*(1-B7) | C39: =B39*12 | D39: =B39/B5 | E39: =B39-(B18+B19+B39*'1. Premissas'!B32) | F39: =E39/B39
A41: A base por estabelecimento é a alavanca de preço mais forte que você tem —
A42: e a que mais assusta rede com muitos endereços. Veja a coluna 'Por trab./mês'.

Sheet 3. Fluxo de caixa
A1: Fluxo de caixa — 24 meses
A2: Movido pelas premissas da aba 1. Cliente médio da aba 1, não o da aba 2.
A4: Mês | B4: 1 | C4: 2 | D4: 3 | E4: 4 | F4: 5 | G4: 6 | H4: 7 | I4: 8 | J4: 9 | K4: 10 | L4: 11 | M4: 12 | N4: 13 | O4: 14 | P4: 15 | Q4: 16 | R4: 17 | S4: 18 | T4: 19 | U4: 20 | V4: 21 | W4: 22 | X4: 23 | Y4: 24
A5: Clientes ativos | B5: ='1. Premissas'!B37+'1. Premissas'!B35 | C5: =B5*(1-'1. Premissas'!B36)+'1. Premissas'!B35 | D5: =C5*(1-'1. Premissas'!B36)+'1. Premissas'!B35 | E5: =D5*(1-'1. Premissas'!B36)+'1. Premissas'!B35 | F5: =E5*(1-'1. Premissas'!B36)+'1. Premissas'!B35 | G5: =F5*(1-'1. Premissas'!B36)+'1. Premissas'!B35 | H5: =G5*(1-'1. Premissas'!B36)+'1. Premissas'!B35 | I5: =H5*(1-'1. Premissas'!B36)+'1. Premissas'!B35 | J5: =I5*(1-'1. Premissas'!B36)+'1. Premissas'!B35 | K5: =J5*(1-'1. Premissas'!B36)+'1. Premissas'!B35 | L5: =K5*(1-'1. Premissas'!B36)+'1. Premissas'!B35 | M5: =L5*(1-'1. Premissas'!B36)+'1. Premissas'!B35 | N5: =M5*(1-'1. Premissas'!B36)+'1. Premissas'!B35 | O5: =N5*(1-'1. Premissas'!B36)+'1. Premissas'!B35 | P5: =O5*(1-'1. Premissas'!B36)+'1. Premissas'!B35 | Q5: =P5*(1-'1. Premissas'!B36)+'1. Premissas'!B35 | R5: =Q5*(1-'1. Premissas'!B36)+'1. Premissas'!B35 | S5: =R5*(1-'1. Premissas'!B36)+'1. Premissas'!B35 | T5: =S5*(1-'1. Premissas'!B36)+'1. Premissas'!B35 | U5: =T5*(1-'1. Premissas'!B36)+'1. Premissas'!B35 | V5: =U5*(1-'1. Premissas'!B36)+'1. Premissas'!B35 | W5: =V5*(1-'1. Premissas'!B36)+'1. Premissas'!B35 | X5: =W5*(1-'1. Premissas'!B36)+'1. Premissas'!B35 | Y5: =X5*(1-'1. Premissas'!B36)+'1. Premissas'!B35
A6: Trabalhadores na base | B6: =B5*'1. Premissas'!B38 | C6: =C5*'1. Premissas'!B38 | D6: =D5*'1. Premissas'!B38 | E6: =E5*'1. Premissas'!B38 | F6: =F5*'1. Premissas'!B38 | G6: =G5*'1. Premissas'!B38 | H6: =H5*'1. Premissas'!B38 | I6: =I5*'1. Premissas'!B38 | J6: =J5*'1. Premissas'!B38 | K6: =K5*'1. Premissas'!B38 | L6: =L5*'1. Premissas'!B38 | M6: =M5*'1. Premissas'!B38 | N6: =N5*'1. Premissas'!B38 | O6: =O5*'1. Premissas'!B38 | P6: =P5*'1. Premissas'!B38 | Q6: =Q5*'1. Premissas'!B38 | R6: =R5*'1. Premissas'!B38 | S6: =S5*'1. Premissas'!B38 | T6: =T5*'1. Premissas'!B38 | U6: =U5*'1. Premissas'!B38 | V6: =V5*'1. Premissas'!B38 | W6: =W5*'1. Premissas'!B38 | X6: =X5*'1. Premissas'!B38 | Y6: =Y5*'1. Premissas'!B38
A7: Receita bruta | B7: =B5*('1. Premissas'!B39*'1. Premissas'!B5+MIN('1. Premissas'!B38,'1. Premissas'!B10)*'1. Premissas'!B6+MAX(0,MIN('1. Premissas'!B38,'1. Premissas'!B11)-'1. Premissas'!B10)*'1. Premissas'!B7+MAX(0,MIN('1. Premissas'!B38,'1. Premissas'!B12)-'1. Premissas'!B11)*'1. Premissas'!B8+MAX(0,'1. Premissas'!B38-'1. Premissas'!B12)*'1. Premissas'!B9)*(1-'1. Premissas'!B40*'1. Premissas'!B18) | C7: =C5*('1. Premissas'!B39*'1. Premissas'!B5+MIN('1. Premissas'!B38,'1. Premissas'!B10)*'1. Premissas'!B6+MAX(0,MIN('1. Premissas'!B38,'1. Premissas'!B11)-'1. Premissas'!B10)*'1. Premissas'!B7+MAX(0,MIN('1. Premissas'!B38,'1. Premissas'!B12)-'1. Premissas'!B11)*'1. Premissas'!B8+MAX(0,'1. Premissas'!B38-'1. Premissas'!B12)*'1. Premissas'!B9)*(1-'1. Premissas'!B40*'1. Premissas'!B18) | D7: =D5*('1. Premissas'!B39*'1. Premissas'!B5+MIN('1. Premissas'!B38,'1. Premissas'!B10)*'1. Premissas'!B6+MAX(0,MIN('1. Premissas'!B38,'1. Premissas'!B11)-'1. Premissas'!B10)*'1. Premissas'!B7+MAX(0,MIN('1. Premissas'!B38,'1. Premissas'!B12)-'1. Premissas'!B11)*'1. Premissas'!B8+MAX(0,'1. Premissas'!B38-'1. Premissas'!B12)*'1. Premissas'!B9)*(1-'1. Premissas'!B40*'1. Premissas'!B18) | E7: =E5*('1. Premissas'!B39*'1. Premissas'!B5+MIN('1. Premissas'!B38,'1. Premissas'!B10)*'1. Premissas'!B6+MAX(0,MIN('1. Premissas'!B38,'1. Premissas'!B11)-'1. Premissas'!B10)*'1. Premissas'!B7+MAX(0,MIN('1. Premissas'!B38,'1. Premissas'!B12)-'1. Premissas'!B11)*'1. Premissas'!B8+MAX(0,'1. Premissas'!B38-'1. Premissas'!B12)*'1. Premissas'!B9)*(1-'1. Premissas'!B40*'1. Premissas'!B18) | F7: =F5*('1. Premissas'!B39*'1. Premissas'!B5+MIN('1. Premissas'!B38,'1. Premissas'!B10)*'1. Premissas'!B6+MAX(0,MIN('1. Premissas'!B38,'1. Premissas'!B11)-'1. Premissas'!B10)*'1. Premissas'!B7+MAX(0,MIN('1. Premissas'!B38,'1. Premissas'!B12)-'1. Premissas'!B11)*'1. Premissas'!B8+MAX(0,'1. Premissas'!B38-'1. Premissas'!B12)*'1. Premissas'!B9)*(1-'1. Premissas'!B40*'1. Premissas'!B18) | G7: =G5*('1. Premissas'!B39*'1. Premissas'!B5+MIN('1. Premissas'!B38,'1. Premissas'!B10)*'1. Premissas'!B6+MAX(0,MIN('1. Premissas'!B38,'1. Premissas'!B11)-'1. Premissas'!B10)*'1. Premissas'!B7+MAX(0,MIN('1. Premissas'!B38,'1. Premissas'!B12)-'1. Premissas'!B11)*'1. Premissas'!B8+MAX(0,'1. Premissas'!B38-'1. Premissas'!B12)*'1. Premissas'!B9)*(1-'1. Premissas'!B40*'1. Premissas'!B18) | H7: =H5*('1. Premissas'!B39*'1. Premissas'!B5+MIN('1. Premissas'!B38,'1. Premissas'!B10)*'1. Premissas'!B6+MAX(0,MIN('1. Premissas'!B38,'1. Premissas'!B11)-'1. Premissas'!B10)*'1. Premissas'!B7+MAX(0,MIN('1. Premissas'!B38,'1. Premissas'!B12)-'1. Premissas'!B11)*'1. Premissas'!B8+MAX(0,'1. Premissas'!B38-'1. Premissas'!B12)*'1. Premissas'!B9)*(1-'1. Premissas'!B40*'1. Premissas'!B18) | I7: =I5*('1. Premissas'!B39*'1. Premissas'!B5+MIN('1. Premissas'!B38,'1. Premissas'!B10)*'1. Premissas'!B6+MAX(0,MIN('1. Premissas'!B38,'1. Premissas'!B11)-'1. Premissas'!B10)*'1. Premissas'!B7+MAX(0,MIN('1. Premissas'!B38,'1. Premissas'!B12)-'1. Premissas'!B11)*'1. Premissas'!B8+MAX(0,'1. Premissas'!B38-'1. Premissas'!B12)*'1. Premissas'!B9)*(1-'1. Premissas'!B40*'1. Premissas'!B18) | J7: =J5*('1. Premissas'!B39*'1. Premissas'!B5+MIN('1. Premissas'!B38,'1. Premissas'!B10)*'1. Premissas'!B6+MAX(0,MIN('1. Premissas'!B38,'1. Premissas'!B11)-'1. Premissas'!B10)*'1. Premissas'!B7+MAX(0,MIN('1. Premissas'!B38,'1. Premissas'!B12)-'1. Premissas'!B11)*'1. Premissas'!B8+MAX(0,'1. Premissas'!B38-'1. Premissas'!B12)*'1. Premissas'!B9)*(1-'1. Premissas'!B40*'1. Premissas'!B18) | K7: =K5*('1. Premissas'!B39*'1. Premissas'!B5+MIN('1. Premissas'!B38,'1. Premissas'!B10)*'1. Premissas'!B6+MAX(0,MIN('1. Premissas'!B38,'1. Premissas'!B11)-'1. Premissas'!B10)*'1. Premissas'!B7+MAX(0,MIN('1. Premissas'!B38,'1. Premissas'!B12)-'1. Premissas'!B11)*'1. Premissas'!B8+MAX(0,'1. Premissas'!B38-'1. Premissas'!B12)*'1. Premissas'!B9)*(1-'1. Premissas'!B40*'1. Premissas'!B18) | L7: =L5*('1. Premissas'!B39*'1. Premissas'!B5+MIN('1. Premissas'!B38,'1. Premissas'!B10)*'1. Premissas'!B6+MAX(0,MIN('1. Premissas'!B38,'1. Premissas'!B11)-'1. Premissas'!B10)*'1. Premissas'!B7+MAX(0,MIN('1. Premissas'!B38,'1. Premissas'!B12)-'1. Premissas'!B11)*'1. Premissas'!B8+MAX(0,'1. Premissas'!B38-'1. Premissas'!B12)*'1. Premissas'!B9)*(1-'1. Premissas'!B40*'1. Premissas'!B18) | M7: =M5*('1. Premissas'!B39*'1. Premissas'!B5+MIN('1. Premissas'!B38,'1. Premissas'!B10)*'1. Premissas'!B6+MAX(0,MIN('1. Premissas'!B38,'1. Premissas'!B11)-'1. Premissas'!B10)*'1. Premissas'!B7+MAX(0,MIN('1. Premissas'!B38,'1. Premissas'!B12)-'1. Premissas'!B11)*'1. Premissas'!B8+MAX(0,'1. Premissas'!B38-'1. Premissas'!B12)*'1. Premissas'!B9)*(1-'1. Premissas'!B40*'1. Premissas'!B18) | N7: =N5*('1. Premissas'!B39*'1. Premissas'!B5+MIN('1. Premissas'!B38,'1. Premissas'!B10)*'1. Premissas'!B6+MAX(0,MIN('1. Premissas'!B38,'1. Premissas'!B11)-'1. Premissas'!B10)*'1. Premissas'!B7+MAX(0,MIN('1. Premissas'!B38,'1. Premissas'!B12)-'1. Premissas'!B11)*'1. Premissas'!B8+MAX(0,'1. Premissas'!B38-'1. Premissas'!B12)*'1. Premissas'!B9)*(1-'1. Premissas'!B40*'1. Premissas'!B18) | O7: =O5*('1. Premissas'!B39*'1. Premissas'!B5+MIN('1. Premissas'!B38,'1. Premissas'!B10)*'1. Premissas'!B6+MAX(0,MIN('1. Premissas'!B38,'1. Premissas'!B11)-'1. Premissas'!B10)*'1. Premissas'!B7+MAX(0,MIN('1. Premissas'!B38,'1. Premissas'!B12)-'1. Premissas'!B11)*'1. Premissas'!B8+MAX(0,'1. Premissas'!B38-'1. Premissas'!B12)*'1. Premissas'!B9)*(1-'1. Premissas'!B40*'1. Premissas'!B18) | P7: =P5*('1. Premissas'!B39*'1. Premissas'!B5+MIN('1. Premissas'!B38,'1. Premissas'!B10)*'1. Premissas'!B6+MAX(0,MIN('1. Premissas'!B38,'1. Premissas'!B11)-'1. Premissas'!B10)*'1. Premissas'!B7+MAX(0,MIN('1. Premissas'!B38,'1. Premissas'!B12)-'1. Premissas'!B11)*'1. Premissas'!B8+MAX(0,'1. Premissas'!B38-'1. Premissas'!B12)*'1. Premissas'!B9)*(1-'1. Premissas'!B40*'1. Premissas'!B18) | Q7: =Q5*('1. Premissas'!B39*'1. Premissas'!B5+MIN('1. Premissas'!B38,'1. Premissas'!B10)*'1. Premissas'!B6+MAX(0,MIN('1. Premissas'!B38,'1. Premissas'!B11)-'1. Premissas'!B10)*'1. Premissas'!B7+MAX(0,MIN('1. Premissas'!B38,'1. Premissas'!B12)-'1. Premissas'!B11)*'1. Premissas'!B8+MAX(0,'1. Premissas'!B38-'1. Premissas'!B12)*'1. Premissas'!B9)*(1-'1. Premissas'!B40*'1. Premissas'!B18) | R7: =R5*('1. Premissas'!B39*'1. Premissas'!B5+MIN('1. Premissas'!B38,'1. Premissas'!B10)*'1. Premissas'!B6+MAX(0,MIN('1. Premissas'!B38,'1. Premissas'!B11)-'1. Premissas'!B10)*'1. Premissas'!B7+MAX(0,MIN('1. Premissas'!B38,'1. Premissas'!B12)-'1. Premissas'!B11)*'1. Premissas'!B8+MAX(0,'1. Premissas'!B38-'1. Premissas'!B12)*'1. Premissas'!B9)*(1-'1. Premissas'!B40*'1. Premissas'!B18) | S7: =S5*('1. Premissas'!B39*'1. Premissas'!B5+MIN('1. Premissas'!B38,'1. Premissas'!B10)*'1. Premissas'!B6+MAX(0,MIN('1. Premissas'!B38,'1. Premissas'!B11)-'1. Premissas'!B10)*'1. Premissas'!B7+MAX(0,MIN('1. Premissas'!B38,'1. Premissas'!B12)-'1. Premissas'!B11)*'1. Premissas'!B8+MAX(0,'1. Premissas'!B38-'1. Premissas'!B12)*'1. Premissas'!B9)*(1-'1. Premissas'!B40*'1. Premissas'!B18) | T7: =T5*('1. Premissas'!B39*'1. Premissas'!B5+MIN('1. Premissas'!B38,'1. Premissas'!B10)*'1. Premissas'!B6+MAX(0,MIN('1. Premissas'!B38,'1. Premissas'!B11)-'1. Premissas'!B10)*'1. Premissas'!B7+MAX(0,MIN('1. Premissas'!B38,'1. Premissas'!B12)-'1. Premissas'!B11)*'1. Premissas'!B8+MAX(0,'1. Premissas'!B38-'1. Premissas'!B12)*'1. Premissas'!B9)*(1-'1. Premissas'!B40*'1. Premissas'!B18) | U7: =U5*('1. Premissas'!B39*'1. Premissas'!B5+MIN('1. Premissas'!B38,'1. Premissas'!B10)*'1. Premissas'!B6+MAX(0,MIN('1. Premissas'!B38,'1. Premissas'!B11)-'1. Premissas'!B10)*'1. Premissas'!B7+MAX(0,MIN('1. Premissas'!B38,'1. Premissas'!B12)-'1. Premissas'!B11)*'1. Premissas'!B8+MAX(0,'1. Premissas'!B38-'1. Premissas'!B12)*'1. Premissas'!B9)*(1-'1. Premissas'!B40*'1. Premissas'!B18) | V7: =V5*('1. Premissas'!B39*'1. Premissas'!B5+MIN('1. Premissas'!B38,'1. Premissas'!B10)*'1. Premissas'!B6+MAX(0,MIN('1. Premissas'!B38,'1. Premissas'!B11)-'1. Premissas'!B10)*'1. Premissas'!B7+MAX(0,MIN('1. Premissas'!B38,'1. Premissas'!B12)-'1. Premissas'!B11)*'1. Premissas'!B8+MAX(0,'1. Premissas'!B38-'1. Premissas'!B12)*'1. Premissas'!B9)*(1-'1. Premissas'!B40*'1. Premissas'!B18) | W7: =W5*('1. Premissas'!B39*'1. Premissas'!B5+MIN('1. Premissas'!B38,'1. Premissas'!B10)*'1. Premissas'!B6+MAX(0,MIN('1. Premissas'!B38,'1. Premissas'!B11)-'1. Premissas'!B10)*'1. Premissas'!B7+MAX(0,MIN('1. Premissas'!B38,'1. Premissas'!B12)-'1. Premissas'!B11)*'1. Premissas'!B8+MAX(0,'1. Premissas'!B38-'1. Premissas'!B12)*'1. Premissas'!B9)*(1-'1. Premissas'!B40*'1. Premissas'!B18) | X7: =X5*('1. Premissas'!B39*'1. Premissas'!B5+MIN('1. Premissas'!B38,'1. Premissas'!B10)*'1. Premissas'!B6+MAX(0,MIN('1. Premissas'!B38,'1. Premissas'!B11)-'1. Premissas'!B10)*'1. Premissas'!B7+MAX(0,MIN('1. Premissas'!B38,'1. Premissas'!B12)-'1. Premissas'!B11)*'1. Premissas'!B8+MAX(0,'1. Premissas'!B38-'1. Premissas'!B12)*'1. Premissas'!B9)*(1-'1. Premissas'!B40*'1. Premissas'!B18) | Y7: =Y5*('1. Premissas'!B39*'1. Premissas'!B5+MIN('1. Premissas'!B38,'1. Premissas'!B10)*'1. Premissas'!B6+MAX(0,MIN('1. Premissas'!B38,'1. Premissas'!B11)-'1. Premissas'!B10)*'1. Premissas'!B7+MAX(0,MIN('1. Premissas'!B38,'1. Premissas'!B12)-'1. Premissas'!B11)*'1. Premissas'!B8+MAX(0,'1. Premissas'!B38-'1. Premissas'!B12)*'1. Premissas'!B9)*(1-'1. Premissas'!B40*'1. Premissas'!B18)
A8: Impostos | B8: =B7*'1. Premissas'!B32 | C8: =C7*'1. Premissas'!B32 | D8: =D7*'1. Premissas'!B32 | E8: =E7*'1. Premissas'!B32 | F8: =F7*'1. Premissas'!B32 | G8: =G7*'1. Premissas'!B32 | H8: =H7*'1. Premissas'!B32 | I8: =I7*'1. Premissas'!B32 | J8: =J7*'1. Premissas'!B32 | K8: =K7*'1. Premissas'!B32 | L8: =L7*'1. Premissas'!B32 | M8: =M7*'1. Premissas'!B32 | N8: =N7*'1. Premissas'!B32 | O8: =O7*'1. Premissas'!B32 | P8: =P7*'1. Premissas'!B32 | Q8: =Q7*'1. Premissas'!B32 | R8: =R7*'1. Premissas'!B32 | S8: =S7*'1. Premissas'!B32 | T8: =T7*'1. Premissas'!B32 | U8: =U7*'1. Premissas'!B32 | V8: =V7*'1. Premissas'!B32 | W8: =W7*'1. Premissas'!B32 | X8: =X7*'1. Premissas'!B32 | Y8: =Y7*'1. Premissas'!B32
A9: Custo variável | B9: =B5*'1. Premissas'!B28+B6*'1. Premissas'!B29 | C9: =C5*'1. Premissas'!B28+C6*'1. Premissas'!B29 | D9: =D5*'1. Premissas'!B28+D6*'1. Premissas'!B29 | E9: =E5*'1. Premissas'!B28+E6*'1. Premissas'!B29 | F9: =F5*'1. Premissas'!B28+F6*'1. Premissas'!B29 | G9: =G5*'1. Premissas'!B28+G6*'1. Premissas'!B29 | H9: =H5*'1. Premissas'!B28+H6*'1. Premissas'!B29 | I9: =I5*'1. Premissas'!B28+I6*'1. Premissas'!B29 | J9: =J5*'1. Premissas'!B28+J6*'1. Premissas'!B29 | K9: =K5*'1. Premissas'!B28+K6*'1. Premissas'!B29 | L9: =L5*'1. Premissas'!B28+L6*'1. Premissas'!B29 | M9: =M5*'1. Premissas'!B28+M6*'1. Premissas'!B29 | N9: =N5*'1. Premissas'!B28+N6*'1. Premissas'!B29 | O9: =O5*'1. Premissas'!B28+O6*'1. Premissas'!B29 | P9: =P5*'1. Premissas'!B28+P6*'1. Premissas'!B29 | Q9: =Q5*'1. Premissas'!B28+Q6*'1. Premissas'!B29 | R9: =R5*'1. Premissas'!B28+R6*'1. Premissas'!B29 | S9: =S5*'1. Premissas'!B28+S6*'1. Premissas'!B29 | T9: =T5*'1. Premissas'!B28+T6*'1. Premissas'!B29 | U9: =U5*'1. Premissas'!B28+U6*'1. Premissas'!B29 | V9: =V5*'1. Premissas'!B28+V6*'1. Premissas'!B29 | W9: =W5*'1. Premissas'!B28+W6*'1. Premissas'!B29 | X9: =X5*'1. Premissas'!B28+X6*'1. Premissas'!B29 | Y9: =Y5*'1. Premissas'!B28+Y6*'1. Premissas'!B29
A10: Custo fixo | B10: ='1. Premissas'!B25 | C10: ='1. Premissas'!B25 | D10: ='1. Premissas'!B25 | E10: ='1. Premissas'!B25 | F10: ='1. Premissas'!B25 | G10: ='1. Premissas'!B25 | H10: ='1. Premissas'!B25 | I10: ='1. Premissas'!B25 | J10: ='1. Premissas'!B25 | K10: ='1. Premissas'!B25 | L10: ='1. Premissas'!B25 | M10: ='1. Premissas'!B25 | N10: ='1. Premissas'!B25 | O10: ='1. Premissas'!B25 | P10: ='1. Premissas'!B25 | Q10: ='1. Premissas'!B25 | R10: ='1. Premissas'!B25 | S10: ='1. Premissas'!B25 | T10: ='1. Premissas'!B25 | U10: ='1. Premissas'!B25 | V10: ='1. Premissas'!B25 | W10: ='1. Premissas'!B25 | X10: ='1. Premissas'!B25 | Y10: ='1. Premissas'!B25
A11: Resultado do mês | B11: =B7-B8-B9-B10 | C11: =C7-C8-C9-C10 | D11: =D7-D8-D9-D10 | E11: =E7-E8-E9-E10 | F11: =F7-F8-F9-F10 | G11: =G7-G8-G9-G10 | H11: =H7-H8-H9-H10 | I11: =I7-I8-I9-I10 | ... Y11: =Y7-Y8-Y9-Y10
A12: Caixa acumulado | B12: =B11 | C12: =B12+C11 | D12: =C12+D11 | E12: =D12+E11 | F12: =E12+F11 | G12: =F12+G11 | H12: =G12+H11 | I12: =H12+I11 | J12: =I12+J11 | ... Y12: =X12+Y11
A14: Ponto de equilíbrio
A15: Clientes necessários para cobrir o fixo | B15: =ROUNDUP('1. Premissas'!B25/(('1. Premissas'!B39*'1. Premissas'!B5+MIN('1. Premissas'!B38,'1. Premissas'!B10)*'1. Premissas'!B6+MAX(0,MIN('1. Premissas'!B38,'1. Premissas'!B11)-'1. Premissas'!B10)*'1. Premissas'!B7+MAX(0,MIN('1. Premissas'!B38,'1. Premissas'!B12)-'1. Premissas'!B11)*'1. Premissas'!B8+MAX(0,'1. Premissas'!B38-'1. Premissas'!B12)*'1. Premissas'!B9)*(1-'1. Premissas'!B40*'1. Premissas'!B18)*(1-'1. Premissas'!B32)-'1. Premissas'!B28-'1. Premissas'!B38*'1. Premissas'!B29),0)
A16: Margem de contribuição por cliente/mês | B16: =(('1. Premissas'!B39*'1. Premissas'!B5+MIN('1. Premissas'!B38,'1. Premissas'!B10)*'1. Premissas'!B6+MAX(0,MIN('1. Premissas'!B38,'1. Premissas'!B11)-'1. Premissas'!B10)*'1. Premissas'!B7+MAX(0,MIN('1. Premissas'!B38,'1. Premissas'!B12)-'1. Premissas'!B11)*'1. Premissas'!B8+MAX(0,'1. Premissas'!B38-'1. Premissas'!B12)*'1. Premissas'!B9)*(1-'1. Premissas'!B40*'1. Premissas'!B18)*(1-'1. Premissas'!B32)-'1. Premissas'!B28-'1. Premissas'!B38*'1. Premissas'!B29)

Sheet 4. Cenários de preço
A1: E se o preço baixar?
A2: Quantos clientes a mais são necessários para manter o mesmo resultado.
A4: Base/estab. | B4: Mensal por cliente | C4: MC por cliente | D4: Clientes p/ equilíbrio | E4: Receita no equilíbrio | F4: Variação vs. tabela
A5: 1200 | B5: =('1. Premissas'!B39*1200+MIN('1. Premissas'!B38,'1. Premissas'!B10)*'1. Premissas'!B6+MAX(0,MIN('1. Premissas'!B38,'1. Premissas'!B11)-'1. Premissas'!B10)*'1. Premissas'!B7+MAX(0,MIN('1. Premissas'!B38,'1. Premissas'!B12)-'1. Premissas'!B11)*'1. Premissas'!B8+MAX(0,'1. Premissas'!B38-'1. Premissas'!B12)*'1. Premissas'!B9)*(1-'1. Premissas'!B40*'1. Premissas'!B18) | C5: =B5*(1-'1. Premissas'!B32)-'1. Premissas'!B28-'1. Premissas'!B38*'1. Premissas'!B29 | D5: =ROUNDUP('1. Premissas'!B25/C5,0) | E5: =D5*B5 | F5: =B5/$B$5-1
A6: 1000 | B6: =('1. Premissas'!B39*1000+MIN('1. Premissas'!B38,'1. Premissas'!B10)*'1. Premissas'!B6+MAX(0,MIN('1. Premissas'!B38,'1. Premissas'!B11)-'1. Premissas'!B10)*'1. Premissas'!B7+MAX(0,MIN('1. Premissas'!B38,'1. Premissas'!B12)-'1. Premissas'!B11)*'1. Premissas'!B8+MAX(0,'1. Premissas'!B38-'1. Premissas'!B12)*'1. Premissas'!B9)*(1-'1. Premissas'!B40*'1. Premissas'!B18) | C6: =B6*(1-'1. Premissas'!B32)-'1. Premissas'!B28-'1. Premissas'!B38*'1. Premissas'!B29 | D6: =ROUNDUP('1. Premissas'!B25/C6,0) | E6: =D6*B6 | F6: =B6/$B$5-1
A7: 900 | B7: =('1. Premissas'!B39*900+MIN('1. Premissas'!B38,'1. Premissas'!B10)*'1. Premissas'!B6+MAX(0,MIN('1. Premissas'!B38,'1. Premissas'!B11)-'1. Premissas'!B10)*'1. Premissas'!B7+MAX(0,MIN('1. Premissas'!B38,'1. Premissas'!B12)-'1. Premissas'!B11)*'1. Premissas'!B8+MAX(0,'1. Premissas'!B38-'1. Premissas'!B12)*'1. Premissas'!B9)*(1-'1. Premissas'!B40*'1. Premissas'!B18) | C7: =B7*(1-'1. Premissas'!B32)-'1. Premissas'!B28-'1. Premissas'!B38*'1. Premissas'!B29 | D7: =ROUNDUP('1. Premissas'!B25/C7,0) | E7: =D7*B7 | F7: =B7/$B$5-1
A8: 800 | B8: =('1. Premissas'!B39*800+MIN('1. Premissas'!B38,'1. Premissas'!B10)*'1. Premissas'!B6+MAX(0,MIN('1. Premissas'!B38,'1. Premissas'!B11)-'1. Premissas'!B10)*'1. Premissas'!B7+MAX(0,MIN('1. Premissas'!B38,'1. Premissas'!B12)-'1. Premissas'!B11)*'1. Premissas'!B8+MAX(0,'1. Premissas'!B38-'1. Premissas'!B12)*'1. Premissas'!B9)*(1-'1. Premissas'!B40*'1. Premissas'!B18) | C8: =B8*(1-'1. Premissas'!B32)-'1. Premissas'!B28-'1. Premissas'!B38*'1. Premissas'!B29 | D8: =ROUNDUP('1. Premissas'!B25/C8,0) | E8: =D8*B8 | F8: =B8/$B$5-1
A9: 700 | B9: =('1. Premissas'!B39*700+MIN('1. Premissas'!B38,'1. Premissas'!B10)*'1. Premissas'!B6+MAX(0,MIN('1. Premissas'!B38,'1. Premissas'!B11)-'1. Premissas'!B10)*'1. Premissas'!B7+MAX(0,MIN('1. Premissas'!B38,'1. Premissas'!B12)-'1. Premissas'!B11)*'1. Premissas'!B8+MAX(0,'1. Premissas'!B38-'1. Premissas'!B12)*'1. Premissas'!B9)*(1-'1. Premissas'!B40*'1. Premissas'!B18) | C9: =B9*(1-'1. Premissas'!B32)-'1. Premissas'!B28-'1. Premissas'!B38*'1. Premissas'!B29 | D9: =ROUNDUP('1. Premissas'!B25/C9,0) | E9: =D9*B9 | F9: =B9/$B$5-1
A10: 600 | B10: =('1. Premissas'!B39*600+MIN('1. Premissas'!B38,'1. Premissas'!B10)*'1. Premissas'!B6+MAX(0,MIN('1. Premissas'!B38,'1. Premissas'!B11)-'1. Premissas'!B10)*'1. Premissas'!B7+MAX(0,MIN('1. Premissas'!B38,'1. Premissas'!B12)-'1. Premissas'!B11)*'1. Premissas'!B8+MAX(0,'1. Premissas'!B38-'1. Premissas'!B12)*'1. Premissas'!B9)*(1-'1. Premissas'!B40*'1. Premissas'!B18) | C10: =B10*(1-'1. Premissas'!B32)-'1. Premissas'!B28-'1. Premissas'!B38*'1. Premissas'!B29 | D10: =ROUNDUP('1. Premissas'!B25/C10,0) | E10: =D10*B10 | F10: =B10/$B$5-1
A11: 500 | B11: =('1. Premissas'!B39*500+MIN('1. Premissas'!B38,'1. Premissas'!B10)*'1. Premissas'!B6+MAX(0,MIN('1. Premissas'!B38,'1. Premissas'!B11)-'1. Premissas'!B10)*'1. Premissas'!B7+MAX(0,MIN('1. Premissas'!B38,'1. Premissas'!B12)-'1. Premissas'!B11)*'1. Premissas'!B8+MAX(0,'1. Premissas'!B38-'1. Premissas'!B12)*'1. Premissas'!B9)*(1-'1. Premissas'!B40*'1. Premissas'!B18) | C11: =B11*(1-'1. Premissas'!B32)-'1. Premissas'!B28-'1. Premissas'!B38*'1. Premissas'!B29 | D11: =ROUNDUP('1. Premissas'!B25/C11,0) | E11: =D11*B11 | F11: =B11/$B$5-1
A12: 400 | B12: =('1. Premissas'!B39*400+MIN('1. Premissas'!B38,'1. Premissas'!B10)*'1. Premissas'!B6+MAX(0,MIN('1. Premissas'!B38,'1. Premissas'!B11)-'1. Premissas'!B10)*'1. Premissas'!B7+MAX(0,MIN('1. Premissas'!B38,'1. Premissas'!B12)-'1. Premissas'!B11)*'1. Premissas'!B8+MAX(0,'1. Premissas'!B38-'1. Premissas'!B12)*'1. Premissas'!B9)*(1-'1. Premissas'!B40*'1. Premissas'!B18) | C12: =B12*(1-'1. Premissas'!B32)-'1. Premissas'!B28-'1. Premissas'!B38*'1. Premissas'!B29 | D12: =ROUNDUP('1. Premissas'!B25/C12,0) | E12: =D12*B12 | F12: =B12/$B$5-1
A13: 300 | B13: =('1. Premissas'!B39*300+MIN('1. Premissas'!B38,'1. Premissas'!B10)*'1. Premissas'!B6+MAX(0,MIN('1. Premissas'!B38,'1. Premissas'!B11)-'1. Premissas'!B10)*'1. Premissas'!B7+MAX(0,MIN('1. Premissas'!B38,'1. Premissas'!B12)-'1. Premissas'!B11)*'1. Premissas'!B8+MAX(0,'1. Premissas'!B38-'1. Premissas'!B12)*'1. Premissas'!B9)*(1-'1. Premissas'!B40*'1. Premissas'!B18) | C13: =B13*(1-'1. Premissas'!B32)-'1. Premissas'!B28-'1. Premissas'!B38*'1. Premissas'!B29 | D13: =ROUNDUP('1. Premissas'!B25/C13,0) | E13: =D13*B13 | F13: =B13/$B$5-1
A15: Como ler esta tabela:
A17: A coluna 'Clientes p/ equilíbrio' é a pergunta comercial de verdade. Baixar o preço só faz
A18: sentido se o número de clientes crescer mais rápido que a queda da margem — e o quanto ele
A19: precisa crescer está ali.
A21: A coluna 'Por trab./mês' da aba 2 é a que o cliente calcula sozinho. É o número com que ele
A22: compara você a qualquer concorrente, e o que ele leva para a reunião de diretoria.
A24: Uma observação sobre a estrutura de preço, e não sobre o valor: cobrar por estabelecimento
A25: penaliza justamente as redes — que são os maiores contratos. Uma empresa com 3.000 lojas paga
A26: por 3.000 bases. Vale simular na aba 2 antes de conversar com varejo ou franquia.
